Workbook

Sheet README
A1: ISV AI Use Case Assessment 入力テンプレート
A2: お客様がAIユースケース・事業/サービス情報をExcelで入力し、Oracle側でAI Use Case Assessmentに利用するためのワークブックです。
A4: 項目 | B4: 内容 | C4: 補足
A5: 目的 | B5: 自社SaaS/パッケージ、保有IP、業務データ、競合差別化、AIで実現したい機能を整理し、AIユースケース評価、OCI構成検討、PoC計画、レポート作成に活用します。 | C5: 入力フォームの回答欄に記入してください。
A6: 入力対象 | B6: 会社・事業概要、Assessment対象範囲、製品・サービス情報、顧客・価格・競合、データ/IP、AIで実現したいこと、AIユースケース候補、技術/OCI、セキュリティ、PoC条件。 | C6: HTMLフォームおよびMicrosoft Forms設計書の10セクションをExcel化しています。
A7: 入力ルール | B7: 水色セルが入力欄です。必須項目はオレンジ表示です。選択式の項目にはプルダウンを設定しています。複数選択の場合は「;」区切りで記入できます。 | C7: 例：SaaS;パッケージ;保守/運用支援
A8: 機密情報 | B8: 個人情報、顧客機密データ、本番データは、Oracle担当者と合意した範囲・手順に従ってください。Excel添付時は提出資料名/リンクのみ記載する運用を推奨します。 | C8: 本テンプレートはアセスメント事前整理用です。
A9: 提出方法 | B9: 入力後、ExcelファイルをSharePoint/Teams/メール等でOracle担当者へ共有してください。必要に応じて「登録用_縦持ち」シートをSharePoint List登録に利用できます。 | C9: SharePoint登録列はForms設計書に合わせています。
A10: 利用シート | B10: ダッシュボード：入力進捗確認。入力フォーム：お客様記入欄。登録用_縦持ち：システム連携/登録用。入力例_エクス：サンプル。選択肢一覧：プルダウン元。Sources：出典。 | C10: 顧客に入力していただく主シートは「入力フォーム」です。

Sheet ダッシュボード
A1: 入力進捗ダッシュボード
A2: 必須項目の入力状況と、セクション別の完了状況を確認できます。
A4: サマリー
A5: 必須項目数 | B5: =COUNTIF('入力フォーム'!C:C,"必須")
A6: 必須入力済 | B6: =COUNTIFS('入力フォーム'!C:C,"必須",'入力フォーム'!E:E,"<>")
A7: 必須未入力 | B7: =B5-B6
A8: 必須入力率 | B8: =IF(B5=0,0,B6/B5)
A9: 任意入力済 | B9: =COUNTIFS('入力フォーム'!C:C,"任意",'入力フォーム'!E:E,"<>")
A12: セクションNo | B12: セクション名 | C12: 必須項目数 | D12: 必須入力済 | E12: 未入力 | F12: 入力率 | G12: 確認ポイント
A13: 0 | B13: 入力前の確認 | C13: =COUNTIFS('入力フォーム'!A:A,A13,'入力フォーム'!C:C,"必須") | D13: =COUNTIFS('入力フォーム'!A:A,A13,'入力フォーム'!C:C,"必須",'入力フォーム'!E:E,"<>") | E13: =C13-D13 | F13: =IF(C13=0,"-",D13/C13) | G13: 未入力がある場合は「入力フォーム」シートの赤/オレンジ表示セルを確認
A14: 1 | B14: 会社・回答者情報 | C14: =COUNTIFS('入力フォーム'!A:A,A14,'入力フォーム'!C:C,"必須") | D14: =COUNTIFS('入力フォーム'!A:A,A14,'入力フォーム'!C:C,"必須",'入力フォーム'!E:E,"<>") | E14: =C14-D14 | F14: =IF(C14=0,"-",D14/C14) | G14: 未入力がある場合は「入力フォーム」シートの赤/オレンジ表示セルを確認
A15: 2 | B15: Assessment対象範囲 | C15: =COUNTIFS('入力フォーム'!A:A,A15,'入力フォーム'!C:C,"必須") | D15: =COUNTIFS('入力フォーム'!A:A,A15,'入力フォーム'!C:C,"必須",'入力フォーム'!E:E,"<>") | E15: =C15-D15 | F15: =IF(C15=0,"-",D15/C15) | G15: 未入力がある場合は「入力フォーム」シートの赤/オレンジ表示セルを確認
A16: 3 | B16: 製品・サービス情報 / ISVアセット・IP | C16: =COUNTIFS('入力フォーム'!A:A,A16,'入力フォーム'!C:C,"必須") | D16: =COUNTIFS('入力フォーム'!A:A,A16,'入力フォーム'!C:C,"必須",'入力フォーム'!E:E,"<>") | E16: =C16-D16 | F16: =IF(C16=0,"-",D16/C16) | G16: 未入力がある場合は「入力フォーム」シートの赤/オレンジ表示セルを確認
A17: 4 | B17: 顧客・価格・競合 | C17: =COUNTIFS('入力フォーム'!A:A,A17,'入力フォーム'!C:C,"必須") | D17: =COUNTIFS('入力フォーム'!A:A,A17,'入力フォーム'!C:C,"必須",'入力フォーム'!E:E,"<>") | E17: =C17-D17 | F17: =IF(C17=0,"-",D17/C17) | G17: 未入力がある場合は「入力フォーム」シートの赤/オレンジ表示セルを確認
A18: 5 | B18: データ/IP・利用条件 | C18: =COUNTIFS('入力フォーム'!A:A,A18,'入力フォーム'!C:C,"必須") | D18: =COUNTIFS('入力フォーム'!A:A,A18,'入力フォーム'!C:C,"必須",'入力フォーム'!E:E,"<>") | E18: =C18-D18 | F18: =IF(C18=0,"-",D18/C18) | G18: 未入力がある場合は「入力フォーム」シートの赤/オレンジ表示セルを確認
A19: 6 | B19: AIで実現したいこと | C19: =COUNTIFS('入力フォーム'!A:A,A19,'入力フォーム'!C:C,"必須") | D19: =COUNTIFS('入力フォーム'!A:A,A19,'入力フォーム'!C:C,"必須",'入力フォーム'!E:E,"<>") | E19: =C19-D19 | F19: =IF(C19=0,"-",D19/C19) | G19: 未入力がある場合は「入力フォーム」シートの赤/オレンジ表示セルを確認
A20: 7 | B20: AIユースケース候補 | C20: =COUNTIFS('入力フォーム'!A:A,A20,'入力フォーム'!C:C,"必須") | D20: =COUNTIFS('入力フォーム'!A:A,A20,'入力フォーム'!C:C,"必須",'入力フォーム'!E:E,"<>") | E20: =C20-D20 | F20: =IF(C20=0,"-",D20/C20) | G20: 未入力がある場合は「入力フォーム」シートの赤/オレンジ表示セルを確認
A21: 8 | B21: 技術・OCI期待範囲 | C21: =COUNTIFS('入力フォーム'!A:A,A21,'入力フォーム'!C:C,"必須") | D21: =COUNTIFS('入力フォーム'!A:A,A21,'入力フォーム'!C:C,"必須",'入力フォーム'!E:E,"<>") | E21: =C21-D21 | F21: =IF(C21=0,"-",D21/C21) | G21: 未入力がある場合は「入力フォーム」シートの赤/オレンジ表示セルを確認
A22: 9 | B22: セキュリティ / ガバナンス | C22: =COUNTIFS('入力フォーム'!A:A,A22,'入力フォーム'!C:C,"必須") | D22: =COUNTIFS('入力フォーム'!A:A,A22,'入力フォーム'!C:C,"必須",'入力フォーム'!E:E,"<>") | E22: =C22-D22 | F22: =IF(C22=0,"-",D22/C22) | G22: 未入力がある場合は「入力フォーム」シートの赤/オレンジ表示セルを確認
A23: 10 | B23: PoC・評価条件・提出資料 | C23: =COUNTIFS('入力フォーム'!A:A,A23,'入力フォーム'!C:C,"必須") | D23: =COUNTIFS('入力フォーム'!A:A,A23,'入力フォーム'!C:C,"必須",'入力フォーム'!E:E,"<>") | E23: =C23-D23 | F23: =IF(C23=0,"-",D23/C23) | G23: 未入力がある場合は「入力フォーム」シートの赤/オレンジ表示セルを確認
A26: 次アクション
A27: 1. 「入力フォーム」シートの水色セルに記入してください。
A28: 2. 必須入力率が100%になったら、必要に応じて提出予定資料名/リンクを記入してください。
A29: 3. Oracle担当者は「登録用_縦持ち」シートをSharePoint List登録/レポート生成用に利用できます。

Sheet 入力フォーム
A1: ISV AI Use Case Assessment 入力フォーム
A2: 水色セルに回答を入力してください。必須項目は未入力時に赤/オレンジで表示されます。複数選択は「;」区切りで記入できます。
A3: 注意：個人情報、顧客機密データ、本番データは、Oracle担当者と合意した範囲・手順に従ってください。添付ファイルは原則としてファイル名/SharePointリンクのみを記載してください。
A5: セクションNo | B5: 質問ID | C5: 必須 | D5: 設問 | E5: 回答入力欄（お客様記入） | F5: 入力ガイド/例 | G5: 入力例（エクス） | H5: 設問タイプ | I5: 選択肢/尺度 | J5: SharePoint列名 | K5: 入力状況
A6: 0. 入力前の確認
A7: 0 | B7: F001 | C7: 必須 | D7: 情報利用目的を確認しましたか？ | F7: 本フォームは、ISV AI Use Case Assessmentの事前整理、AIユースケース評価、OCI構成検討、PoC計画、レポート作成に利用します。 | H7: Choice（単一選択） | I7: 確認しました | J7: ConsentPurpose | K7: =IF($B7="","",IF($C7="必須",IF(LEN(TRIM($E7))>0,"OK","未入力"),IF(LEN(TRIM($E7))>0,"入力済","任意")))
A8: 0 | B8: F002 | C8: 必須 | D8: 本番データ・顧客機密データ・個人情報をアップロードしないことを確認しましたか？ | F8: 添付資料は、Oracle担当者と合意した範囲の資料に限定してください。 | H8: Choice（単一選択） | I8: 確認しました | J8: ConsentNoSensitiveUpload | K8: =IF($B8="","",IF($C8="必須",IF(LEN(TRIM($E8))>0,"OK","未入力"),IF(LEN(TRIM($E8))>0,"入力済","任意")))
A9: 1. 会社・回答者情報
A10: 1 | B10: F101 | C10: 必須 | D10: 会社名 | F10: 例：株式会社〇〇 | G10: 株式会社エクス | H10: Text（短い回答） | J10: CompanyName | K10: =IF($B10="","",IF($C10="必須",IF(LEN(TRIM($E10))>0,"OK","未入力"),IF(LEN(TRIM($E10))>0,"入力済","任意")))
A11: 1 | B11: F102 | C11: 任意 | D11: 会社URL | F11: 例：https://www.example.co.jp/ | G11: https://www.xeex.co.jp/ | H11: Text（短い回答） | J11: CompanyURL | K11: =IF($B11="","",IF($C11="必須",IF(LEN(TRIM($E11))>0,"OK","未入力"),IF(LEN(TRIM($E11))>0,"入力済","任意")))
A12: 1 | B12: F103 | C12: 必須 | D12: 事業概要 | F12: 製品単体ではなく、周辺サービス、導入支援、運用支援も含めて記入してください。 | G12: 製造業向けの生産管理パッケージを中核に、製造業向けクラウドサービス/プラットフォーム、DX関連サービス、導入コンサルティング、カスタマイズ開発、稼働支援、保守を提供するソフトウェアベンダー。 | H12: Text（長い回答） | J12: BusinessOverview | K12: =IF($B12="","",IF($C12="必須",IF(LEN(TRIM($E12))>0,"OK","未入力"),IF(LEN(TRIM($E12))>0,"入力済","任意")))
A13: 1 | B13: F104 | C13: 必須 | D13: 主な顧客像 | F13: 例：中堅・中小製造業、従業員100〜3,000名、工場/生産管理部門/購買部門 | G13: 中堅・中小の製造業。生産管理、購買、在庫、現場、販売管理などの部門が主な利用者。 | H13: Text（長い回答） | J13: MainCustomers | K13: =IF($B13="","",IF($C13="必須",IF(LEN(TRIM($E13))>0,"OK","未入力"),IF(LEN(TRIM($E13))>0,"入力済","任意")))
A14: 1 | B14: F105 | C14: 任意 | D14: 対象業種・業態 | F14: 複数選択可。その他の場合は自由記述を併用してください。 | G14: 製造業;生産管理;販売管理;サプライチェーン;調達・購買 | H14: Choice（複数選択） | I14: 製造業;流通/小売;金融;医療/ヘルスケア;公共;建設;バックオフィス;物流/SCM;教育;不動産;その他 | J14: IndustrySegments | K14: =IF($B14="","",IF($C14="必須",IF(LEN(TRIM($E14))>0,"OK","未入力"),IF(LEN(TRIM($E14))>0,"入力済","任意")))
A15: 1 | B15: F106 | C15: 任意 | D15: 自社の強み・保有IP | F15: 例：業界特化の業務ロジック、マスタ管理、導入ノウハウ、既存顧客データ、テンプレート | G15: 生産・販売統合型の業務ロジック、製造業向けマスタ/実績データ、導入実績、周辺DXソリューションとの接続可能性。 | H15: Text（長い回答） | J15: BusinessStrengthIP | K15: =IF($B15="","",IF($C15="必須",IF(LEN(TRIM($E15))>0,"OK","未入力"),IF(LEN(TRIM($E15))>0,"入力済","任意")))
A16: 1 | B16: F107 | C16: 必須 | D16: 入力者氏名 | F16: 例：山田 太郎 | H16: Text（短い回答） | J16: RespondentName | K16: =IF($B16="","",IF($C16="必須",IF(LEN(TRIM($E16))>0,"OK","未入力"),IF(LEN(TRIM($E16))>0,"入力済","任意")))
A17: 1 | B17: F108 | C17: 必須 | D17: 入力者メール | F17: 例：name@example.co.jp | H17: Text（短い回答） | J17: RespondentEmail | K17: =IF($B17="","",IF($C17="必須",IF(LEN(TRIM($E17))>0,"OK","未入力"),IF(LEN(TRIM($E17))>0,"入力済","任意")))
A18: 1 | B18: F109 | C18: 任意 | D18: 入力者所属/役職 | F18: 例：CTO、プロダクト責任者、開発責任者、営業責任者 | H18: Text（短い回答） | J18: RespondentRole | K18: =IF($B18="","",IF($C18="必須",IF(LEN(TRIM($E18))>0,"OK","未入力"),IF(LEN(TRIM($E18))>0,"入力済","任意")))
A19: 2. Assessment対象範囲
A20: 2 | B20: F201 | C20: 必須 | D20: 今回のAssessment対象範囲 | F20: 既存サービスに加え、本番環境構築中・開発中・構想中の新サービスも対象にできます。 | H20: Choice（複数選択） | I20: 既存SaaS/クラウドサービス;既存パッケージ;新規サービス/新規SaaS;本番環境構築中;開発中;構想中;複数プロジェクト横断 | J20: AssessmentScope | K20: =IF($B20="","",IF($C20="必須",IF(LEN(TRIM($E20))>0,"OK","未入力"),IF(LEN(TRIM($E20))>0,"入力済","任意")))
A21: 2 | B21: F202 | C21: 任意 | D21: 対象プロジェクト数 | F21: Microsoft Formsでは最大3件分の入力欄を用意しています。3件超の場合は補足欄に記入してください。 | H21: Choice（単一選択） | I21: 1件;2件;3件以上;未定 | J21: ProjectCount | K21: =IF($B21="","",IF($C21="必須",IF(LEN(TRIM($E21))>0,"OK","未入力"),IF(LEN(TRIM($E21))>0,"入力済","任意")))
A22: 2 | B22: F211 | C22: 必須 | D22: プロジェクト1：プロジェクト/製品名 | F22: 例：既存SaaS、構築中サービス、開発中プロダクト | G22: Factory-ONE 電脳工場 データ活用 | H22: Text（短い回答） | J22: Project1Name | K22: =IF($B22="","",IF($C22="必須",IF(LEN(TRIM($E22))>0,"OK","未入力"),IF(LEN(TRIM($E22))>0,"入力済","任意")))
A23: 2 | B23: F212 | C23: 必須 | D23: プロジェクト1：段階 | F23: 現在の開発/運用段階を選択してください。 | G23: 本番運用中 | H23: Choice（単一選択） | I23: 本番運用中;本番環境構築中;開発中;構想中;PoC中;未定 | J23: Project1Stage | K23: =IF($B23="","",IF($C23="必須",IF(LEN(TRIM($E23))>0,"OK","未入力"),IF(LEN(TRIM($E23))>0,"入力済","任意")))
A24: 2 | B24: F213 | C24: 必須 | D24: プロジェクト1：優先度 | F24: 現時点の優先度で構いません。 | G24: 高 | H24: Choice（単一選択） | I24: 高;中;低;未定 | J24: Project1Priority | K24: =IF($B24="","",IF($C24="必須",IF(LEN(TRIM($E24))>0,"OK","未入力"),IF(LEN(TRIM($E24))>0,"入力済","任意")))
A25: 2 | B25: F214 | C25: 必須 | D25: プロジェクト1：AI活用の狙い・確認したいこと | F25: 例：データ活用、AI機能を初期リリースに含めるか、運用データ蓄積後に段階導入するか | G25: 既存データを活用し、需給・在庫、生産計画、原価・調達のAIユースケースを検討する。 | H25: Text（長い回答） | J25: Project1AIIntent | K25: =IF($B25="","",IF($C25="必須",IF(LEN(TRIM($E25))>0,"OK","未入力"),IF(LEN(TRIM($E25))>0,"入力済","任意")))
A26: 2 | B26: F221 | C26: 任意 | D26: プロジェクト2：プロジェクト/製品名 | F26: 例：既存SaaS、構築中サービス、開発中プロダクト | G26: こうばWith | H26: Text（短い回答） | J26: Project2Name | K26: =IF($B26="","",IF($C26="必須",IF(LEN(TRIM($E26))>0,"OK","未入力"),IF(LEN(TRIM($E26))>0,"入力済","任意")))
A27: 2 | B27: F222 | C27: 任意 | D27: プロジェクト2：段階 | F27: 現在の開発/運用段階を選択してください。 | G27: 本番環境構築中 | H27: Choice（単一選択） | I27: 本番運用中;本番環境構築中;開発中;構想中;PoC中;未定 | J27: Project2Stage | K27: =IF($B27="","",IF($C27="必須",IF(LEN(TRIM($E27))>0,"OK","未入力"),IF(LEN(TRIM($E27))>0,"入力済","任意")))
A28: 2 | B28: F223 | C28: 任意 | D28: プロジェクト2：優先度 | F28: 現時点の優先度で構いません。 | G28: 中 | H28: Choice（単一選択） | I28: 高;中;低;未定 | J28: Project2Priority | K28: =IF($B28="","",IF($C28="必須",IF(LEN(TRIM($E28))>0,"OK","未入力"),IF(LEN(TRIM($E28))>0,"入力済","任意")))
A29: 2 | B29: F224 | C29: 任意 | D29: プロジェクト2：AI活用の狙い・確認したいこと | F29: 例：データ活用、AI機能を初期リリースに含めるか、運用データ蓄積後に段階導入するか | G29: 本番データの種類、保持場所、テナント構成、運用監視、AI機能の段階導入可否を確認する。 | H29: Text（長い回答） | J29: Project2AIIntent | K29: =IF($B29="","",IF($C29="必須",IF(LEN(TRIM($E29))>0,"OK","未入力"),IF(LEN(TRIM($E29))>0,"入力済","任意")))
A30: 2 | B30: F231 | C30: 任意 | D30: プロジェクト3：プロジェクト/製品名 | F30: 例：既存SaaS、構築中サービス、開発中プロダクト | G30: Endeval（旧Endevor） | H30: Text（短い回答） | J30: Project3Name | K30: =IF($B30="","",IF($C30="必須",IF(LEN(TRIM($E30))>0,"OK","未入力"),IF(LEN(TRIM($E30))>0,"入力済","任意")))
A31: 2 | B31: F232 | C31: 任意 | D31: プロジェクト3：段階 | F31: 現在の開発/運用段階を選択してください。 | G31: 開発中 | H31: Choice（単一選択） | I31: 本番運用中;本番環境構築中;開発中;構想中;PoC中;未定 | J31: Project3Stage | K31: =IF($B31="","",IF($C31="必須",IF(LEN(TRIM($E31))>0,"OK","未入力"),IF(LEN(TRIM($E31))>0,"入力済","任意")))
A32: 2 | B32: F233 | C32: 任意 | D32: プロジェクト3：優先度 | F32: 現時点の優先度で構いません。 | G32: 中 | H32: Choice（単一選択） | I32: 高;中;低;未定 | J32: Project3Priority | K32: =IF($B32="","",IF($C32="必須",IF(LEN(TRIM($E32))>0,"OK","未入力"),IF(LEN(TRIM($E32))>0,"入力済","任意")))
A33: 2 | B33: F234 | C33: 任意 | D33: プロジェクト3：AI活用の狙い・確認したいこと | F33: 例：データ活用、AI機能を初期リリースに含めるか、運用データ蓄積後に段階導入するか | G33: 構成検討中のため、事業目的、対象業務、アーキテクチャ、AI活用の狙いを整理する。 | H33: Text（長い回答） | J33: Project3AIIntent | K33: =IF($B33="","",IF($C33="必須",IF(LEN(TRIM($E33))>0,"OK","未入力"),IF(LEN(TRIM($E33))>0,"入力済","任意")))
A34: 3. 製品・サービス情報 / ISVアセット・IP
A35: 3 | B35: F301 | C35: 必須 | D35: 主対象製品/サービス名 | F35: 例：生産管理SaaS、EDIサービス、グループウェア、周辺ソリューション | G35: Factory-ONE 電脳工場 | H35: Text（短い回答） | J35: PrimaryProductName | K35: =IF($B35="","",IF($C35="必須",IF(LEN(TRIM($E35))>0,"OK","未入力"),IF(LEN(TRIM($E35))>0,"入力済","任意")))
A36: 3 | B36: F302 | C36: 任意 | D36: 提供形態 | F36: 複数選択可。 | G36: パッケージ;クラウドサービス | H36: Choice（複数選択） | I36: SaaS;パッケージ;オンプレミス;クラウドサービス;プラットフォーム;導入支援/コンサル;保守/運用支援;その他 | J36: DeliveryModel | K36: =IF($B36="","",IF($C36="必須",IF(LEN(TRIM($E36))>0,"OK","未入力"),IF(LEN(TRIM($E36))>0,"入力済","任意")))
A37: 3 | B37: F303 | C37: 任意 | D37: 位置づけ・提供価値 | F37: 例：中堅・中小製造業向けの生産・販売統合型システム | G37: 中堅・中小製造業向けの生産・販売統合型の生産管理システム。 | H37: Text（長い回答） | J37: ProductPositioning | K37: =IF($B37="","",IF($C37="必須",IF(LEN(TRIM($E37))>0,"OK","未入力"),IF(LEN(TRIM($E37))>0,"入力済","任意")))
A38: 3 | B38: F304 | C38: 必須 | D38: 代表的な機能・業務範囲 | F38: 例：受注、出荷、生産計画、発注、受入、在庫、進捗、原価、請求 | G38: 生産計画、受注・出荷、手配計画、発注、受入、在庫、負荷、進捗、原価、請求、売掛、入金、仕入、買掛、支払。 | H38: Text（長い回答） | J38: ProductFunctions | K38: =IF($B38="","",IF($C38="必須",IF(LEN(TRIM($E38))>0,"OK","未入力"),IF(LEN(TRIM($E38))>0,"入力済","任意")))
A39: 3 | B39: F305 | C39: 必須 | D39: 関連データ領域 | F39: 例：マスタ、実績、履歴、文書、外部データ、取引先データ | G39: 品目、BOM、取引先、工程などのマスタ、受注/生産/在庫/購買/原価などの実績、納期変更履歴、EDI受注取込。 | H39: Text（長い回答） | J39: DataDomains | K39: =IF($B39="","",IF($C39="必須",IF(LEN(TRIM($E39))>0,"OK","未入力"),IF(LEN(TRIM($E39))>0,"入力済","任意")))
A40: 3 | B40: F306 | C40: 任意 | D40: 関連/拡張ソリューション | F40: 例：在庫診断、価格シミュレータ、現品照合、帳票、スケジューラ | G40: EX在庫診断/EX在庫シミュレータ、EX調達価格シミュレータ、EXQR現品照合。 | H40: Text（長い回答） | J40: RelatedSolutions | K40: =IF($B40="","",IF($C40="必須",IF(LEN(TRIM($E40))>0,"OK","未入力"),IF(LEN(TRIM($E40))>0,"入力済","任意")))
A41: 3 | B41: F307 | C41: 任意 | D41: カスタマイズ/個社対応の状況 | F41: 例：ソース公開、個社カスタマイズあり、共通機能化可能な範囲 | G41: パッケージでありつつソース公開を行い、利用企業側でのカスタマイズも可能。共通AI機能と個社固有拡張の切り分けが必要。 | H41: Text（長い回答） | J41: CustomizationStatus | K41: =IF($B41="","",IF($C41="必須",IF(LEN(TRIM($E41))>0,"OK","未入力"),IF(LEN(TRIM($E41))>0,"入力済","任意")))
A42: 3 | B42: F308 | C42: 任意 | D42: 追加対象製品・サービスがあれば記入してください | F42: 複数製品を横断して評価したい場合に記入してください。 | G42: EXtelligence EDIFAS：クラウド型EDI（調達・購買）サービス。見積、受発注、入出荷、API/CSV連携、電子帳簿保存法対応ストレージ保存。 | H42: Text（長い回答） | J42: AdditionalProducts | K42: =IF($B42="","",IF($C42="必須",IF(LEN(TRIM($E42))>0,"OK","未入力"),IF(LEN(TRIM($E42))>0,"入力済","任意")))
A43: 4. 顧客・価格・競合
A44: 4 | B44: F401 | C44: 任意 | D44: ターゲット顧客規模 | F44: 複数選択可。 | G44: 中堅企業;SMB | H44: Choice（複数選択） | I44: SMB;中堅企業;大企業;エンタープライズ;公共;海外;未定 | J44: CustomerScale | K44: =IF($B44="","",IF($C44="必須",IF(LEN(TRIM($E44))>0,"OK","未入力"),IF(LEN(TRIM($E44))>0,"入力済","任意")))
A45: 4 | B45: F402 | C45: 任意 | D45: 価格形態 | F45: 現行サービスの価格形態を選択してください。 | G45: 月額サブスクリプション;保守費;個別見積 | H45: Choice（複数選択） | I45: 月額サブスクリプション;年額サブスクリプション;ユーザー課金;テナント課金;API/利用量課金;初期費用;保守費;ライセンス買い切り;個別見積 | J45: PricingModel | K45: =IF($B45="","",IF($C45="必須",IF(LEN(TRIM($E45))>0,"OK","未入力"),IF(LEN(TRIM($E45))>0,"入力済","任意")))
A46: 4 | B46: F403 | C46: 任意 | D46: ライセンス形式 | F46: 該当するライセンス形式を選択してください。 | H46: Choice（複数選択） | I46: Named User;Concurrent User;Site License;Tenant License;Device/拠点課金;API Call;Transaction;その他 | J46: LicenseModel | K46: =IF($B46="","",IF($C46="必須",IF(LEN(TRIM($E46))>0,"OK","未入力"),IF(LEN(TRIM($E46))>0,"入力済","任意")))
A47: 4 | B47: F404 | C47: 任意 | D47: 現行収益モデル | F47: 例：月額利用料、導入支援、カスタマイズ、保守、オプション機能 | G47: パッケージ/クラウド利用料、導入コンサルティング、カスタマイズ開発、稼働支援、保守。 | H47: Text（長い回答） | J47: CurrentRevenueModel | K47: =IF($B47="","",IF($C47="必須",IF(LEN(TRIM($E47))>0,"OK","未入力"),IF(LEN(TRIM($E47))>0,"入力済","任意")))
A48: 4 | B48: F405 | C48: 任意 | D48: AI機能の想定収益モデル | F48: 現時点の仮説で構いません。 | G48: AIアドオン;上位プラン;AI Agent実行回数課金;標準機能化による解約率低減 | H48: Choice（複数選択） | I48: AIアドオン;上位プラン;利用量課金;AI Agent実行回数課金;帳票/文書処理件数課金;成果/業務KPI連動;標準機能化による解約率低減;未定 | J48: AIRevenueModel | K48: =IF($B48="","",IF($C48="必須",IF(LEN(TRIM($E48))>0,"OK","未入力"),IF(LEN(TRIM($E48))>0,"入力済","任意")))
A49: 4 | B49: F406 | C49: 任意 | D49: 主な競合製品・競合企業 | F49: 例：競合A、競合B、内製システム、特定業界PKG | G49: 同業生産管理パッケージ、ERP、製造業向けSaaS、内製システム。詳細は顧客ヒアリングで確認。 | H49: Text（長い回答） | J49: Competitors | K49: =IF($B49="","",IF($C49="必須",IF(LEN(TRIM($E49))>0,"OK","未入力"),IF(LEN(TRIM($E49))>0,"入力済","任意")))
A50: 4 | B50: F407 | C50: 任意 | D50: 競合と比較したAI差別化仮説 | F50: 断定ではなく現時点の仮説で構いません。公開情報、勝ち負け理由、自社データで差別化できる領域を記入してください。 | G50: 生産管理・販売管理・EDI・現場帳票などのデータを横断し、需要予測、納期遅延予兆、在庫リスク、調達価格影響を説明できるAI機能を提供することで差別化する仮説。 | H50: Text（長い回答） | J50: CompetitiveAIDifferentiation | K50: =IF($B50="","",IF($C50="必須",IF(LEN(TRIM($E50))>0,"OK","未入力"),IF(LEN(TRIM($E50))>0,"入力済","任意")))
A51: 4 | B51: F408 | C51: 任意 | D51: 市場投入上の課題・懸念 | F51: 例：価格、競合、社内体制、営業説明、顧客のAI利用許諾、サポート体制 | H51: Text（長い回答） | J51: GTMChallenges | K51: =IF($B51="","",IF($C51="必須",IF(LEN(TRIM($E51))>0,"OK","未入力"),IF(LEN(TRIM($E51))>0,"入力済","任意")))
A52: 5. データ/IP・利用条件
A53: 5 | B53: F501 | C53: 必須 | D53: 保有データ・業務IP | F53: AI活用に使えそうなマスタ、実績、履歴、文書、業務ルール、ノウハウを記入してください。 | G53: 品目マスタ、BOM、取引先、工程、受注、出荷、生産計画、発注、受入、在庫、負荷、進捗、原価、請求、売掛、入金、仕入、買掛、支払、EDI取引、現場帳票、問い合わせ/マニュアル。 | H53: Text（長い回答） | J53: DataAssetsIP | K53: =IF($B53="","",IF($C53="必須",IF(LEN(TRIM($E53))>0,"OK","未入力"),IF(LEN(TRIM($E53))>0,"入力済","任意")))
A54: 5 | B54: F502 | C54: 任意 | D54: データ種別 | F54: 複数選択可。 | G54: マスタデータ;トランザクション;文書/PDF/マニュアル;外部データ/API;複数企業間データ | H54: Choice（複数選択） | I54: マスタデータ;トランザクション;文書/PDF/マニュアル;ログ/利用履歴;画像/図面/帳票;音声/会話;外部データ/API;複数企業間データ;個人情報/機密情報を含む | J54: DataTypes | K54: =IF($B54="","",IF($C54="必須",IF(LEN(TRIM($E54))>0,"OK","未入力"),IF(LEN(TRIM($E54))>0,"入力済","任意")))
A55: 5 | B55: F503 | C55: 任意 | D55: データの所在・保持場所 | F55: 複数選択可。 | G55: 自社SaaS DB;顧客環境;外部基幹システム;EDI/外部取引基盤;ファイル/文書ストレージ | H55: Choice（複数選択） | I55: 自社SaaS DB;顧客環境;外部基幹システム;ファイル/文書ストレージ;DWH/Datamart;Object Storage;EDI/外部取引基盤;未定 | J55: DataLocation | K55: =IF($B55="","",IF($C55="必須",IF(LEN(TRIM($E55))>0,"OK","未入力"),IF(LEN(TRIM($E55))>0,"入力済","任意")))
A56: 5 | B56: F504 | C56: 任意 | D56: データ形式・連携方式 | F56: 複数選択可。 | G56: RDB;CSV;API;EDI;PDF/文書;画像/帳票 | H56: Choice（複数選択） | I56: RDB;CSV;API;EDI;PDF/文書;画像/帳票;ログ;音声;その他 | J56: DataFormat | K56: =IF($B56="","",IF($C56="必須",IF(LEN(TRIM($E56))>0,"OK","未入力"),IF(LEN(TRIM($E56))>0,"入力済","任意")))
A57: 5 | B57: F505 | C57: 任意 | D57: データ量・更新頻度・品質 | F57: 例：履歴期間、件数、欠損、表記揺れ、マスタ整備状況、更新頻度 | G57: データ量、履歴期間、欠損、表記揺れ、マスタ整備状況、更新頻度は初回ヒアリングで確認。 | H57: Text（長い回答） | J57: DataVolumeQuality | K57: =IF($B57="","",IF($C57="必須",IF(LEN(TRIM($E57))>0,"OK","未入力"),IF(LEN(TRIM($E57))>0,"入力済","任意")))
A58: 5 | B58: F506 | C58: 任意 | D58: テナント分離・顧客データ方針 | F58: 例：顧客テナントごとのデータ分離、顧客別DB、論理分離、共有データの有無 | G58: 顧客テナントごとのデータ分離、顧客データ利用許諾、匿名化/マスキング方針を確認。 | H58: Text（長い回答） | J58: TenantDataPolicy | K58: =IF($B58="","",IF($C58="必須",IF(LEN(TRIM($E58))>0,"OK","未入力"),IF(LEN(TRIM($E58))>0,"入力済","任意")))
A59: 5 | B59: F507 | C59: 任意 | D59: データ利用許諾・匿名化/マスキング | F59: 例：PoC利用可否、匿名化データ、サンプルデータ、顧客同意範囲 | G59: PoCで利用可能なサンプルデータ、匿名化データ、本番データ利用可否、顧客同意範囲を確認。 | H59: Text（長い回答） | J59: DataUsageConsent | K59: =IF($B59="","",IF($C59="必須",IF(LEN(TRIM($E59))>0,"OK","未入力"),IF(LEN(TRIM($E59))>0,"入力済","任意")))
A60: 5 | B60: F508 | C60: 任意 | D60: 複数企業/取引先データの取り扱い | F60: EDI/サプライチェーン等で複数企業にまたがる場合、所有権、同意、共有範囲を記入してください。 | G60: EDIFAS等の複数企業データについて、利用目的、データ所有権、同意、越境/共有範囲を最初に整理する。 | H60: Text（長い回答） | J60: MultiCompanyDataPolicy | K60: =IF($B60="","",IF($C60="必須",IF(LEN(TRIM($E60))>0,"OK","未入力"),IF(LEN(TRIM($E60))>0,"入力済","任意")))
A61: 5 | B61: F509_1 | C61: 任意 | D61: データ成熟度：必要データが存在する | F61: 未整理 / 一部整理 / 整理済み / 検証済み / 不明 から選択してください。 | H61: Choice（単一選択） | I61: 未整理;一部整理;整理済み;検証済み;不明 | J61: DataReadinessCheck1 | K61: =IF($B61="","",IF($C61="必須",IF(LEN(TRIM($E61))>0,"OK","未入力"),IF(LEN(TRIM($E61))>0,"入力済","任意")))
A62: 5 | B62: F509_2 | C62: 任意 | D62: データ成熟度：データ項目定義が明確 | F62: 未整理 / 一部整理 / 整理済み / 検証済み / 不明 から選択してください。 | H62: Choice（単一選択） | I62: 未整理;一部整理;整理済み;検証済み;不明 | J62: DataReadinessCheck2 | K62: =IF($B62="","",IF($C62="必須",IF(LEN(TRIM($E62))>0,"OK","未入力"),IF(LEN(TRIM($E62))>0,"入力済","任意")))
A63: 5 | B63: F509_3 | C63: 任意 | D63: データ成熟度：データ品質を把握している | F63: 未整理 / 一部整理 / 整理済み / 検証済み / 不明 から選択してください。 | H63: Choice（単一選択） | I63: 未整理;一部整理;整理済み;検証済み;不明 | J63: DataReadinessCheck3 | K63: =IF($B63="","",IF($C63="必須",IF(LEN(TRIM($E63))>0,"OK","未入力"),IF(LEN(TRIM($E63))>0,"入力済","任意")))
A64: 5 | B64: F509_4 | C64: 任意 | D64: データ成熟度：顧客データ利用許諾が整理済み | F64: 未整理 / 一部整理 / 整理済み / 検証済み / 不明 から選択してください。 | H64: Choice（単一選択） | I64: 未整理;一部整理;整理済み;検証済み;不明 | J64: DataReadinessCheck4 | K64: =IF($B64="","",IF($C64="必須",IF(LEN(TRIM($E64))>0,"OK","未入力"),IF(LEN(TRIM($E64))>0,"入力済","任意")))
A65: 5 | B65: F509_5 | C65: 任意 | D65: データ成熟度：匿名化・マスキング方針がある | F65: 未整理 / 一部整理 / 整理済み / 検証済み / 不明 から選択してください。 | H65: Choice（単一選択） | I65: 未整理;一部整理;整理済み;検証済み;不明 | J65: DataReadinessCheck5 | K65: =IF($B65="","",IF($C65="必須",IF(LEN(TRIM($E65))>0,"OK","未入力"),IF(LEN(TRIM($E65))>0,"入力済","任意")))
A66: 5 | B66: F509_6 | C66: 任意 | D66: データ成熟度：API・連携方式がある | F66: 未整理 / 一部整理 / 整理済み / 検証済み / 不明 から選択してください。 | H66: Choice（単一選択） | I66: 未整理;一部整理;整理済み;検証済み;不明 | J66: DataReadinessCheck6 | K66: =IF($B66="","",IF($C66="必須",IF(LEN(TRIM($E66))>0,"OK","未入力"),IF(LEN(TRIM($E66))>0,"入力済","任意")))
A67: 6. AIで実現したいこと
A68: 6 | B68: F601 | C68: 必須 | D68: AI活用目的 | F68: 複数選択可。 | G68: 新サービス開発・収益増;競合差別化;業務効率化・運用効率化;顧客体験向上;コスト/原価率改善 | H68: Choice（複数選択） | I68: 新サービス開発・収益増;競合差別化;業務効率化・運用効率化;顧客体験向上;従業員体験向上;コスト/原価率改善;リスク低減・品質向上;開発生産性向上 | J68: AIObjectives | K68: =IF($B68="","",IF($C68="必須",IF(LEN(TRIM($E68))>0,"OK","未入力"),IF(LEN(TRIM($E68))>0,"入力済","任意")))
A69: 6 | B69: F602 | C69: 必須 | D69: AIで何を行いたいか | F69: 例：需給・在庫の予測、問い合わせ対応、自然言語検索、文書生成、業務支援Agent | G69: 需給・在庫の予測、欠品/過剰在庫リスク検知、納期遅延予兆、負荷偏り検知、調達価格変動の利益影響予測、製造・生産管理の問い合わせ対応、マニュアル/過去事例検索。 | H69: Text（長い回答） | J69: WhatToDoWithAI | K69: =IF($B69="","",IF($C69="必須",IF(LEN(TRIM($E69))>0,"OK","未入力"),IF(LEN(TRIM($E69))>0,"入力済","任意")))
A70: 6 | B70: F603 | C70: 任意 | D70: 期待するAI機能・サービス内容 | F70: 複数選択可。 | G70: RAG/ナレッジ検索;自然言語でのデータ問い合わせ;予測;異常検知;AI Agentによる業務実行支援;文書/帳票生成 | H70: Choice（複数選択） | I70: RAG/ナレッジ検索;自然言語でのデータ問い合わせ;要約;文書/帳票生成;予測;異常検知;最適化/推薦;画像・帳票認識;音声/議事録;AI Agentによる業務実行支援;コード/開発支援;運用監視 | J70: AIFeatureExpectations | K70: =IF($B70="","",IF($C70="必須",IF(LEN(TRIM($E70))>0,"OK","未入力"),IF(LEN(TRIM($E70))>0,"入力済","任意")))
A71: 6 | B71: F604 | C71: 任意 | D71: AIの実行レベル | F71: AIがどこまで行う想定かを選択してください。 | G71: 提案・推奨まで | H71: Choice（単一選択） | I71: 説明/回答のみ;提案・推奨まで;人間承認後に実行;条件付きで自動実行;完全自動実行を検討;未定 | J71: AIExecutionLevel | K71: =IF($B71="","",IF($C71="必須",IF(LEN(TRIM($E71))>0,"OK","未入力"),IF(LEN(TRIM($E71))>0,"入力済","任意")))
A72: 6 | B72: F605 | C72: 任意 | D72: 人による確認/承認が必要な場面 | F72: 例：発注、計画変更、価格提示、外部通知、顧客データ参照、法令判断 | G72: 計画変更、発注、外部通知、価格提示、顧客データをまたぐ分析は人間承認を前提とする。 | H72: Text（長い回答） | J72: HumanInLoop | K72: =IF($B72="","",IF($C72="必須",IF(LEN(TRIM($E72))>0,"OK","未入力"),IF(LEN(TRIM($E72))>0,"入力済","任意")))
A73: 6 | B73: F606 | C73: 任意 | D73: 期待するKPI/ビジネス効果 | F73: 例：問い合わせ一次解決率、回答精度、業務時間削減、在庫削減、納期遵守率、ARPU向上、解約率低下 | G73: 在庫削減、欠品/過剰在庫の抑制、納期遵守率向上、問い合わせ対応時間削減、計画変更判断の迅速化、AI機能による新規収益化。 | H73: Text（長い回答） | J73: BusinessKPI | K73: =IF($B73="","",IF($C73="必須",IF(LEN(TRIM($E73))>0,"OK","未入力"),IF(LEN(TRIM($E73))>0,"入力済","任意")))
A74: 6 | B74: F607 | C74: 任意 | D74: AI機能の想定利用者 | F74: 複数選択可。 | H74: Choice（複数選択） | I74: エンドユーザー;管理者;経営/管理職;サポート担当;開発/運用担当;顧客企業のIT部門;取引先/サプライヤー;その他 | J74: AIUserPersona | K74: =IF($B74="","",IF($C74="必須",IF(LEN(TRIM($E74))>0,"OK","未入力"),IF(LEN(TRIM($E74))>0,"入力済","任意")))
A75: 7. AIユースケース候補
A76: 7 | B76: F711 | C76: 必須 | D76: ユースケース1：名称 | F76: 例：需要予測・在庫最適化、納期遅延予兆、AI業務アシスタント | G76: 需要予測・在庫最適化 | H76: Text（短い回答） | J76: UseCase1Name | K76: =IF($B76="","",IF($C76="必須",IF(LEN(TRIM($E76))>0,"OK","未入力"),IF(LEN(TRIM($E76))>0,"入力済","任意")))
A77: 7 | B77: F712 | C77: 必須 | D77: ユースケース1：業務領域 | F77: 該当する業務領域を選択してください。 | G77: 需給・在庫 | H77: Choice（単一選択） | I77: 需給・在庫;生産計画・進捗;原価・調達;業務支援;サプライチェーン;製品開発・運用;カスタマーサポート;セキュリティ;その他 | J77: UseCase1Domain | K77: =IF($B77="","",IF($C77="必須",IF(LEN(TRIM($E77))>0,"OK","未入力"),IF(LEN(TRIM($E77))>0,"入力済","任意")))
A78: 7 | B78: F713 | C78: 必須 | D78: ユースケース1：優先度 | F78: 現時点の優先度で構いません。 | G78: 高 | H78: Choice（単一選択） | I78: 高;中;低;未定 | J78: UseCase1Priority | K78: =IF($B78="","",IF($C78="必須",IF(LEN(TRIM($E78))>0,"OK","未入力"),IF(LEN(TRIM($E78))>0,"入力済","任意")))
A79: 7 | B79: F714 | C79: 必須 | D79: ユースケース1：利用シナリオ | F79: 誰が、どの業務で、どのようにAIを利用するかを記入してください。 | G79: 販売/受注/在庫履歴から将来需要を予測し、安全在庫・発注点を提案する。 | H79: Text（長い回答） | J79: UseCase1Scenario | K79: =IF($B79="","",IF($C79="必須",IF(LEN(TRIM($E79))>0,"OK","未入力"),IF(LEN(TRIM($E79))>0,"入力済","任意")))
A80: 7 | B80: F715 | C80: 必須 | D80: ユースケース1：必要データ | F80: 例：販売/受注履歴、在庫、品目、BOM、リードタイム、マニュアル、FAQ | G80: 販売/受注履歴、在庫、品目、BOM、リードタイム、発注履歴、季節性データ。 | H80: Text（長い回答） | J80: UseCase1RequiredData | K80: =IF($B80="","",IF($C80="必須",IF(LEN(TRIM($E80))>0,"OK","未入力"),IF(LEN(TRIM($E80))>0,"入力済","任意")))
A81: 7 | B81: F716 | C81: 任意 | D81: ユースケース1：想定AI技術 | F81: 複数選択可。 | G81: 予測/時系列分析;生成AI;データ可視化 | H81: Choice（複数選択） | I81: 生成AI;RAG;Vector Search;AI Agent;自然言語SQL/NL2SQL;予測/時系列分析;異常検知;最適化;画像認識;文書理解/OCR;音声認識;データ可視化;Human-in-the-loop | J81: UseCase1AITech | K81: =IF($B81="","",IF($C81="必須",IF(LEN(TRIM($E81))>0,"OK","未入力"),IF(LEN(TRIM($E81))>0,"入力済","任意")))
A82: 7 | B82: F717 | C82: 任意 | D82: ユースケース1：期待効果/KPI | F82: 例：在庫削減率、欠品率、問い合わせ一次解決率、サポート工数削減 | G82: 在庫削減率、欠品率、過剰在庫額、発注判断時間。 | H82: Text（長い回答） | J82: UseCase1ImpactKPI | K82: =IF($B82="","",IF($C82="必須",IF(LEN(TRIM($E82))>0,"OK","未入力"),IF(LEN(TRIM($E82))>0,"入力済","任意")))
A83: 7 | B83: F721 | C83: 任意 | D83: ユースケース2：名称 | F83: 例：需要予測・在庫最適化、納期遅延予兆、AI業務アシスタント | G83: 納期遅延予兆・計画変更影響説明 | H83: Text（短い回答） | J83: UseCase2Name | K83: =IF($B83="","",IF($C83="必須",IF(LEN(TRIM($E83))>0,"OK","未入力"),IF(LEN(TRIM($E83))>0,"入力済","任意")))
A84: 7 | B84: F722 | C84: 任意 | D84: ユースケース2：業務領域 | F84: 該当する業務領域を選択してください。 | G84: 生産計画・進捗 | H84: Choice（単一選択） | I84: 需給・在庫;生産計画・進捗;原価・調達;業務支援;サプライチェーン;製品開発・運用;カスタマーサポート;セキュリティ;その他 | J84: UseCase2Domain | K84: =IF($B84="","",IF($C84="必須",IF(LEN(TRIM($E84))>0,"OK","未入力"),IF(LEN(TRIM($E84))>0,"入力済","任意")))
A85: 7 | B85: F723 | C85: 任意 | D85: ユースケース2：優先度 | F85: 現時点の優先度で構いません。 | G85: 高 | H85: Choice（単一選択） | I85: 高;中;低;未定 | J85: UseCase2Priority | K85: =IF($B85="","",IF($C85="必須",IF(LEN(TRIM($E85))>0,"OK","未入力"),IF(LEN(TRIM($E85))>0,"入力済","任意")))
A86: 7 | B86: F724 | C86: 任意 | D86: ユースケース2：利用シナリオ | F86: 誰が、どの業務で、どのようにAIを利用するかを記入してください。 | G86: 生産計画、進捗、負荷、在庫、購買状況をもとに遅延リスクを検知し、影響範囲を自然言語で説明する。 | H86: Text（長い回答） | J86: UseCase2Scenario | K86: =IF($B86="","",IF($C86="必須",IF(LEN(TRIM($E86))>0,"OK","未入力"),IF(LEN(TRIM($E86))>0,"入力済","任意")))
A87: 7 | B87: F725 | C87: 任意 | D87: ユースケース2：必要データ | F87: 例：販売/受注履歴、在庫、品目、BOM、リードタイム、マニュアル、FAQ | G87: 生産計画、進捗、負荷、工程、受注、納期変更履歴、購買/在庫。 | H87: Text（長い回答） | J87: UseCase2RequiredData | K87: =IF($B87="","",IF($C87="必須",IF(LEN(TRIM($E87))>0,"OK","未入力"),IF(LEN(TRIM($E87))>0,"入力済","任意")))
A88: 7 | B88: F726 | C88: 任意 | D88: ユースケース2：想定AI技術 | F88: 複数選択可。 | G88: 異常検知;予測/時系列分析;生成AI;RAG | H88: Choice（複数選択） | I88: 生成AI;RAG;Vector Search;AI Agent;自然言語SQL/NL2SQL;予測/時系列分析;異常検知;最適化;画像認識;文書理解/OCR;音声認識;データ可視化;Human-in-the-loop | J88: UseCase2AITech | K88: =IF($B88="","",IF($C88="必須",IF(LEN(TRIM($E88))>0,"OK","未入力"),IF(LEN(TRIM($E88))>0,"入力済","任意")))
A89: 7 | B89: F727 | C89: 任意 | D89: ユースケース2：期待効果/KPI | F89: 例：在庫削減率、欠品率、問い合わせ一次解決率、サポート工数削減 | G89: 納期遵守率、遅延検知リードタイム、計画変更工数。 | H89: Text（長い回答） | J89: UseCase2ImpactKPI | K89: =IF($B89="","",IF($C89="必須",IF(LEN(TRIM($E89))>0,"OK","未入力"),IF(LEN(TRIM($E89))>0,"入力済","任意")))
A90: 7 | B90: F731 | C90: 任意 | D90: ユースケース3：名称 | F90: 例：需要予測・在庫最適化、納期遅延予兆、AI業務アシスタント | G90: 製造業務AIアシスタント | H90: Text（短い回答） | J90: UseCase3Name | K90: =IF($B90="","",IF($C90="必須",IF(LEN(TRIM($E90))>0,"OK","未入力"),IF(LEN(TRIM($E90))>0,"入力済","任意")))
A91: 7 | B91: F732 | C91: 任意 | D91: ユースケース3：業務領域 | F91: 該当する業務領域を選択してください。 | G91: 業務支援 | H91: Choice（単一選択） | I91: 需給・在庫;生産計画・進捗;原価・調達;業務支援;サプライチェーン;製品開発・運用;カスタマーサポート;セキュリティ;その他 | J91: UseCase3Domain | K91: =IF($B91="","",IF($C91="必須",IF(LEN(TRIM($E91))>0,"OK","未入力"),IF(LEN(TRIM($E91))>0,"入力済","任意")))
A92: 7 | B92: F733 | C92: 任意 | D92: ユースケース3：優先度 | F92: 現時点の優先度で構いません。 | G92: 中 | H92: Choice（単一選択） | I92: 高;中;低;未定 | J92: UseCase3Priority | K92: =IF($B92="","",IF($C92="必須",IF(LEN(TRIM($E92))>0,"OK","未入力"),IF(LEN(TRIM($E92))>0,"入力済","任意")))
A93: 7 | B93: F734 | C93: 任意 | D93: ユースケース3：利用シナリオ | F93: 誰が、どの業務で、どのようにAIを利用するかを記入してください。 | G93: ユーザーが自然言語で操作方法、過去事例、在庫/受注/生産状況を問い合わせ、根拠付き回答を受け取る。 | H93: Text（長い回答） | J93: UseCase3Scenario | K93: =IF($B93="","",IF($C93="必須",IF(LEN(TRIM($E93))>0,"OK","未入力"),IF(LEN(TRIM($E93))>0,"入力済","任意")))
A94: 7 | B94: F735 | C94: 任意 | D94: ユースケース3：必要データ | F94: 例：販売/受注履歴、在庫、品目、BOM、リードタイム、マニュアル、FAQ | G94: 製品マニュアル、FAQ、過去問い合わせ、業務データ、権限情報。 | H94: Text（長い回答） | J94: UseCase3RequiredData | K94: =IF($B94="","",IF($C94="必須",IF(LEN(TRIM($E94))>0,"OK","未入力"),IF(LEN(TRIM($E94))>0,"入力済","任意")))
A95: 7 | B95: F736 | C95: 任意 | D95: ユースケース3：想定AI技術 | F95: 複数選択可。 | G95: RAG;Vector Search;生成AI;Human-in-the-loop | H95: Choice（複数選択） | I95: 生成AI;RAG;Vector Search;AI Agent;自然言語SQL/NL2SQL;予測/時系列分析;異常検知;最適化;画像認識;文書理解/OCR;音声認識;データ可視化;Human-in-the-loop | J95: UseCase3AITech | K95: =IF($B95="","",IF($C95="必須",IF(LEN(TRIM($E95))>0,"OK","未入力"),IF(LEN(TRIM($E95))>0,"入力済","任意")))
A96: 7 | B96: F737 | C96: 任意 | D96: ユースケース3：期待効果/KPI | F96: 例：在庫削減率、欠品率、問い合わせ一次解決率、サポート工数削減 | G96: 問い合わせ一次解決率、回答精度、サポート工数削減、顧客満足度。 | H96: Text（長い回答） | J96: UseCase3ImpactKPI | K96: =IF($B96="","",IF($C96="必須",IF(LEN(TRIM($E96))>0,"OK","未入力"),IF(LEN(TRIM($E96))>0,"入力済","任意")))
A97: 8. 技術・OCI期待範囲
A98: 8 | B98: F801 | C98: 任意 | D98: 現行アーキテクチャ概要 | F98: クラウド、DB、API、認証、テナント構成、外部連携、画面/バックエンド構成を記入してください。 | G98: 現行プラットフォーム、DB、API、認証、テナント構成、データ連携図を確認。 | H98: Text（長い回答） | J98: CurrentArchitecture | K98: =IF($B98="","",IF($C98="必須",IF(LEN(TRIM($E98))>0,"OK","未入力"),IF(LEN(TRIM($E98))>0,"入力済","任意")))
A99: 8 | B99: F802 | C99: 任意 | D99: 利用中クラウド/基盤 | F99: 複数選択可。 | H99: Choice（複数選択） | I99: AWS;Azure;Google Cloud;OCI;オンプレミス;自社DC;SaaS/PaaS;未定/非公開 | J99: CurrentCloudPlatform | K99: =IF($B99="","",IF($C99="必須",IF(LEN(TRIM($E99))>0,"OK","未入力"),IF(LEN(TRIM($E99))>0,"入力済","任意")))
A100: 8 | B100: F803 | C100: 任意 | D100: 利用中DB/データ基盤 | F100: 複数選択可。 | H100: Choice（複数選択） | I100: Oracle Database;PostgreSQL;MySQL;SQL Server;NoSQL;DWH;Data Lake;Search Engine;その他 | J100: CurrentDBPlatform | K100: =IF($B100="","",IF($C100="必須",IF(LEN(TRIM($E100))>0,"OK","未入力"),IF(LEN(TRIM($E100))>0,"入力済","任意")))
A101: 8 | B101: F804 | C101: 任意 | D101: API・認証・外部連携 | F101: 例：REST API、CSV連携、EDI、SAML/OIDC、顧客別認証、外部基幹システム連携 | G101: 外部基幹システムとのAPI/CSV連携、EDI、認証、権限制御、既存業務画面との連携方式を確認。 | H101: Text（長い回答） | J101: APIAuthIntegration | K101: =IF($B101="","",IF($C101="必須",IF(LEN(TRIM($E101))>0,"OK","未入力"),IF(LEN(TRIM($E101))>0,"入力済","任意")))
...

Sheet 登録用_縦持ち
A1: 登録用_縦持ち
A2: 「入力フォーム」シートの回答を質問ID単位で参照する登録用テーブルです。SharePoint Listや後続処理への取り込みに利用できます。
A4: 表示順 | B4: セクションNo | C4: セクション名 | D4: 質問ID | E4: 設問 | F4: SharePoint列名 | G4: 必須 | H4: 回答値
A5: 1 | B5: 0 | C5: 入力前の確認 | D5: F001 | E5: 情報利用目的を確認しましたか？ | F5: ConsentPurpose | G5: 必須 | H5: ='入力フォーム'!E7
A6: 2 | B6: 0 | C6: 入力前の確認 | D6: F002 | E6: 本番データ・顧客機密データ・個人情報をアップロードしないことを確認しましたか？ | F6: ConsentNoSensitiveUpload | G6: 必須 | H6: ='入力フォーム'!E8
A7: 3 | B7: 1 | C7: 会社・回答者情報 | D7: F101 | E7: 会社名 | F7: CompanyName | G7: 必須 | H7: ='入力フォーム'!E10
A8: 4 | B8: 1 | C8: 会社・回答者情報 | D8: F102 | E8: 会社URL | F8: CompanyURL | G8: 任意 | H8: ='入力フォーム'!E11
A9: 5 | B9: 1 | C9: 会社・回答者情報 | D9: F103 | E9: 事業概要 | F9: BusinessOverview | G9: 必須 | H9: ='入力フォーム'!E12
A10: 6 | B10: 1 | C10: 会社・回答者情報 | D10: F104 | E10: 主な顧客像 | F10: MainCustomers | G10: 必須 | H10: ='入力フォーム'!E13
A11: 7 | B11: 1 | C11: 会社・回答者情報 | D11: F105 | E11: 対象業種・業態 | F11: IndustrySegments | G11: 任意 | H11: ='入力フォーム'!E14
A12: 8 | B12: 1 | C12: 会社・回答者情報 | D12: F106 | E12: 自社の強み・保有IP | F12: BusinessStrengthIP | G12: 任意 | H12: ='入力フォーム'!E15
A13: 9 | B13: 1 | C13: 会社・回答者情報 | D13: F107 | E13: 入力者氏名 | F13: RespondentName | G13: 必須 | H13: ='入力フォーム'!E16
A14: 10 | B14: 1 | C14: 会社・回答者情報 | D14: F108 | E14: 入力者メール | F14: RespondentEmail | G14: 必須 | H14: ='入力フォーム'!E17
A15: 11 | B15: 1 | C15: 会社・回答者情報 | D15: F109 | E15: 入力者所属/役職 | F15: RespondentRole | G15: 任意 | H15: ='入力フォーム'!E18
A16: 12 | B16: 2 | C16: Assessment対象範囲 | D16: F201 | E16: 今回のAssessment対象範囲 | F16: AssessmentScope | G16: 必須 | H16: ='入力フォーム'!E20
A17: 13 | B17: 2 | C17: Assessment対象範囲 | D17: F202 | E17: 対象プロジェクト数 | F17: ProjectCount | G17: 任意 | H17: ='入力フォーム'!E21
A18: 14 | B18: 2 | C18: Assessment対象範囲 | D18: F211 | E18: プロジェクト1：プロジェクト/製品名 | F18: Project1Name | G18: 必須 | H18: ='入力フォーム'!E22
A19: 15 | B19: 2 | C19: Assessment対象範囲 | D19: F212 | E19: プロジェクト1：段階 | F19: Project1Stage | G19: 必須 | H19: ='入力フォーム'!E23
A20: 16 | B20: 2 | C20: Assessment対象範囲 | D20: F213 | E20: プロジェクト1：優先度 | F20: Project1Priority | G20: 必須 | H20: ='入力フォーム'!E24
A21: 17 | B21: 2 | C21: Assessment対象範囲 | D21: F214 | E21: プロジェクト1：AI活用の狙い・確認したいこと | F21: Project1AIIntent | G21: 必須 | H21: ='入力フォーム'!E25
A22: 18 | B22: 2 | C22: Assessment対象範囲 | D22: F221 | E22: プロジェクト2：プロジェクト/製品名 | F22: Project2Name | G22: 任意 | H22: ='入力フォーム'!E26
A23: 19 | B23: 2 | C23: Assessment対象範囲 | D23: F222 | E23: プロジェクト2：段階 | F23: Project2Stage | G23: 任意 | H23: ='入力フォーム'!E27
A24: 20 | B24: 2 | C24: Assessment対象範囲 | D24: F223 | E24: プロジェクト2：優先度 | F24: Project2Priority | G24: 任意 | H24: ='入力フォーム'!E28
A25: 21 | B25: 2 | C25: Assessment対象範囲 | D25: F224 | E25: プロジェクト2：AI活用の狙い・確認したいこと | F25: Project2AIIntent | G25: 任意 | H25: ='入力フォーム'!E29
A26: 22 | B26: 2 | C26: Assessment対象範囲 | D26: F231 | E26: プロジェクト3：プロジェクト/製品名 | F26: Project3Name | G26: 任意 | H26: ='入力フォーム'!E30
A27: 23 | B27: 2 | C27: Assessment対象範囲 | D27: F232 | E27: プロジェクト3：段階 | F27: Project3Stage | G27: 任意 | H27: ='入力フォーム'!E31
... A29: 25 | B29: 2 | C29: Assessment対象範囲 | D29: F234 | E29: プロジェクト3：AI活用の狙い・確認したいこと | F29: Project3AIIntent | G29: 任意 | H29: ='入力フォーム'!E33
A30: 26 | B30: 3 | C30: 製品・サービス情報 / ISVアセット・IP | D30: F301 | E30: 主対象製品/サービス名 | F30: PrimaryProductName | G30: 必須 | H30: ='入力フォーム'!E35
A31: 27 | B31: 3 | C31: 製品・サービス情報 / ISVアセット・IP | D31: F302 | E31: 提供形態 | F31: DeliveryModel | G31: 任意 | H31: ='入力フォーム'!E36
A32: 28 | B32: 3 | C32: 製品・サービス情報 / ISVアセット・IP | D32: F303 | E32: 位置づけ・提供価値 | F32: ProductPositioning | G32: 任意 | H32: ='入力フォーム'!E37
A33: 29 | B33: 3 | C33: 製品・サービス情報 / ISVアセット・IP | D33: F304 | E33: 代表的な機能・業務範囲 | F33: ProductFunctions | G33: 必須 | H33: ='入力フォーム'!E38
A34: 30 | B34: 3 | C34: 製品・サービス情報 / ISVアセット・IP | D34: F305 | E34: 関連データ領域 | F34: DataDomains | G34: 必須 | H34: ='入力フォーム'!E39
A35: 31 | B35: 3 | C35: 製品・サービス情報 / ISVアセット・IP | D35: F306 | E35: 関連/拡張ソリューション | F35: RelatedSolutions | G35: 任意 | H35: ='入力フォーム'!E40
A36: 32 | B36: 3 | C36: 製品・サービス情報 / ISVアセット・IP | D36: F307 | E36: カスタマイズ/個社対応の状況 | F36: CustomizationStatus | G36: 任意 | H36: ='入力フォーム'!E41
A37: 33 | B37: 3 | C37: 製品・サービス情報 / ISVアセット・IP | D37: F308 | E37: 追加対象製品・サービスがあれば記入してください | F37: AdditionalProducts | G37: 任意 | H37: ='入力フォーム'!E42
A38: 34 | B38: 4 | C38: 顧客・価格・競合 | D38: F401 | E38: ターゲット顧客規模 | F38: CustomerScale | G38: 任意 | H38: ='入力フォーム'!E44
A39: 35 | B39: 4 | C39: 顧客・価格・競合 | D39: F402 | E39: 価格形態 | F39: PricingModel | G39: 任意 | H39: ='入力フォーム'!E45
A40: 36 | B40: 4 | C40: 顧客・価格・競合 | D40: F403 | E40: ライセンス形式 | F40: LicenseModel | G40: 任意 | H40: ='入力フォーム'!E46
A41: 37 | B41: 4 | C41: 顧客・価格・競合 | D41: F404 | E41: 現行収益モデル | F41: CurrentRevenueModel | G41: 任意 | H41: ='入力フォーム'!E47
A42: 38 | B42: 4 | C42: 顧客・価格・競合 | D42: F405 | E42: AI機能の想定収益モデル | F42: AIRevenueModel | G42: 任意 | H42: ='入力フォーム'!E48
A43: 39 | B43: 4 | C43: 顧客・価格・競合 | D43: F406 | E43: 主な競合製品・競合企業 | F43: Competitors | G43: 任意 | H43: ='入力フォーム'!E49
A44: 40 | B44: 4 | C44: 顧客・価格・競合 | D44: F407 | E44: 競合と比較したAI差別化仮説 | F44: CompetitiveAIDifferentiation | G44: 任意 | H44: ='入力フォーム'!E50
A45: 41 | B45: 4 | C45: 顧客・価格・競合 | D45: F408 | E45: 市場投入上の課題・懸念 | F45: GTMChallenges | G45: 任意 | H45: ='入力フォーム'!E51
A46: 42 | B46: 5 | C46: データ/IP・利用条件 | D46: F501 | E46: 保有データ・業務IP | F46: DataAssetsIP | G46: 必須 | H46: ='入力フォーム'!E53
A47: 43 | B47: 5 | C47: データ/IP・利用条件 | D47: F502 | E47: データ種別 | F47: DataTypes | G47: 任意 | H47: ='入力フォーム'!E54
A48: 44 | B48: 5 | C48: データ/IP・利用条件 | D48: F503 | E48: データの所在・保持場所 | F48: DataLocation | G48: 任意 | H48: ='入力フォーム'!E55
A49: 45 | B49: 5 | C49: データ/IP・利用条件 | D49: F504 | E49: データ形式・連携方式 | F49: DataFormat | G49: 任意 | H49: ='入力フォーム'!E56
A50: 46 | B50: 5 | C50: データ/IP・利用条件 | D50: F505 | E50: データ量・更新頻度・品質 | F50: DataVolumeQuality | G50: 任意 | H50: ='入力フォーム'!E57
A51: 47 | B51: 5 | C51: データ/IP・利用条件 | D51: F506 | E51: テナント分離・顧客データ方針 | F51: TenantDataPolicy | G51: 任意 | H51: ='入力フォーム'!E58
A52: 48 | B52: 5 | C52: データ/IP・利用条件 | D52: F507 | E52: データ利用許諾・匿名化/マスキング | F52: DataUsageConsent | G52: 任意 | H52: ='入力フォーム'!E59
A53: 49 | B53: 5 | C53: データ/IP・利用条件 | D53: F508 | E53: 複数企業/取引先データの取り扱い | F53: MultiCompanyDataPolicy | G53: 任意 | H53: ='入力フォーム'!E60
A54: 50 | B54: 5 | C54: データ/IP・利用条件 | D54: F509_1 | E54: データ成熟度：必要データが存在する | F54: DataReadinessCheck1 | G54: 任意 | H54: ='入力フォーム'!E61
A55: 51 | B55: 5 | C55: データ/IP・利用条件 | D55: F509_2 | E55: データ成熟度：データ項目定義が明確 | F55: DataReadinessCheck2 | G55: 任意 | H55: ='入力フォーム'!E62
A56: 52 | B56: 5 | C56: データ/IP・利用条件 | D56: F509_3 | E56: データ成熟度：データ品質を把握している | F56: DataReadinessCheck3 | G56: 任意 | H56: ='入力フォーム'!E63
A57: 53 | B57: 5 | C57: データ/IP・利用条件 | D57: F509_4 | E57: データ成熟度：顧客データ利用許諾が整理済み | F57: DataReadinessCheck4 | G57: 任意 | H57: ='入力フォーム'!E64
... A59: 55 | B59: 5 | C59: データ/IP・利用条件 | D59: F509_6 | E59: データ成熟度：API・連携方式がある | F59: DataReadinessCheck6 | G59: 任意 | H59: ='入力フォーム'!E66
A60: 56 | B60: 6 | C60: AIで実現したいこと | D60: F601 | E60: AI活用目的 | F60: AIObjectives | G60: 必須 | H60: ='入力フォーム'!E68
A61: 57 | B61: 6 | C61: AIで実現したいこと | D61: F602 | E61: AIで何を行いたいか | F61: WhatToDoWithAI | G61: 必須 | H61: ='入力フォーム'!E69
A62: 58 | B62: 6 | C62: AIで実現したいこと | D62: F603 | E62: 期待するAI機能・サービス内容 | F62: AIFeatureExpectations | G62: 任意 | H62: ='入力フォーム'!E70
A63: 59 | B63: 6 | C63: AIで実現したいこと | D63: F604 | E63: AIの実行レベル | F63: AIExecutionLevel | G63: 任意 | H63: ='入力フォーム'!E71
A64: 60 | B64: 6 | C64: AIで実現したいこと | D64: F605 | E64: 人による確認/承認が必要な場面 | F64: HumanInLoop | G64: 任意 | H64: ='入力フォーム'!E72
A65: 61 | B65: 6 | C65: AIで実現したいこと | D65: F606 | E65: 期待するKPI/ビジネス効果 | F65: BusinessKPI | G65: 任意 | H65: ='入力フォーム'!E73
A66: 62 | B66: 6 | C66: AIで実現したいこと | D66: F607 | E66: AI機能の想定利用者 | F66: AIUserPersona | G66: 任意 | H66: ='入力フォーム'!E74
A67: 63 | B67: 7 | C67: AIユースケース候補 | D67: F711 | E67: ユースケース1：名称 | F67: UseCase1Name | G67: 必須 | H67: ='入力フォーム'!E76
A68: 64 | B68: 7 | C68: AIユースケース候補 | D68: F712 | E68: ユースケース1：業務領域 | F68: UseCase1Domain | G68: 必須 | H68: ='入力フォーム'!E77
A69: 65 | B69: 7 | C69: AIユースケース候補 | D69: F713 | E69: ユースケース1：優先度 | F69: UseCase1Priority | G69: 必須 | H69: ='入力フォーム'!E78
A70: 66 | B70: 7 | C70: AIユースケース候補 | D70: F714 | E70: ユースケース1：利用シナリオ | F70: UseCase1Scenario | G70: 必須 | H70: ='入力フォーム'!E79
A71: 67 | B71: 7 | C71: AIユースケース候補 | D71: F715 | E71: ユースケース1：必要データ | F71: UseCase1RequiredData | G71: 必須 | H71: ='入力フォーム'!E80
A72: 68 | B72: 7 | C72: AIユースケース候補 | D72: F716 | E72: ユースケース1：想定AI技術 | F72: UseCase1AITech | G72: 任意 | H72: ='入力フォーム'!E81
A73: 69 | B73: 7 | C73: AIユースケース候補 | D73: F717 | E73: ユースケース1：期待効果/KPI | F73: UseCase1ImpactKPI | G73: 任意 | H73: ='入力フォーム'!E82
A74: 70 | B74: 7 | C74: AIユースケース候補 | D74: F721 | E74: ユースケース2：名称 | F74: UseCase2Name | G74: 任意 | H74: ='入力フォーム'!E83
A75: 71 | B75: 7 | C75: AIユースケース候補 | D75: F722 | E75: ユースケース2：業務領域 | F75: UseCase2Domain | G75: 任意 | H75: ='入力フォーム'!E84
A76: 72 | B76: 7 | C76: AIユースケース候補 | D76: F723 | E76: ユースケース2：優先度 | F76: UseCase2Priority | G76: 任意 | H76: ='入力フォーム'!E85
A77: 73 | B77: 7 | C77: AIユースケース候補 | D77: F724 | E77: ユースケース2：利用シナリオ | F77: UseCase2Scenario | G77: 任意 | H77: ='入力フォーム'!E86
A78: 74 | B78: 7 | C78: AIユースケース候補 | D78: F725 | E78: ユースケース2：必要データ | F78: UseCase2RequiredData | G78: 任意 | H78: ='入力フォーム'!E87
... A87: 83 | B87: 7 | C87: AIユースケース候補 | D87: F737 | E87: ユースケース3：期待効果/KPI | F87: UseCase3ImpactKPI | G87: 任意 | H87: ='入力フォーム'!E96
A88: 84 | B88: 8 | C88: 技術・OCI期待範囲 | D88: F801 | E88: 現行アーキテクチャ概要 | F88: CurrentArchitecture | G88: 任意 | H88: ='入力フォーム'!E98
A89: 85 | B89: 8 | C89: 技術・OCI期待範囲 | D89: F802 | E89: 利用中クラウド/基盤 | F89: CurrentCloudPlatform | G89: 任意 | H89: ='入力フォーム'!E99
A90: 86 | B90: 8 | C90: 技術・OCI期待範囲 | D90: F803 | E90: 利用中DB/データ基盤 | F90: CurrentDBPlatform | G90: 任意 | H90: ='入力フォーム'!E100
A91: 87 | B91: 8 | C91: 技術・OCI期待範囲 | D91: F804 | E91: API・認証・外部連携 | F91: APIAuthIntegration | G91: 任意 | H91: ='入力フォーム'!E101
A92: 88 | B92: 8 | C92: 技術・OCI期待範囲 | D92: F805 | E92: OCI上で求める範囲 | F92: OCIScope | G92: 任意 | H92: ='入力フォーム'!E102
A93: 89 | B93: 8 | C93: 技術・OCI期待範囲 | D93: F806 | E93: 非機能要件 | F93: NonFunctionalRequirements | G93: 任意 | H93: ='入力フォーム'!E103
A94: 90 | B94: 8 | C94: 技術・OCI期待範囲 | D94: F807 | E94: 既存制約・移行条件 | F94: ExistingConstraints | G94: 任意 | H94: ='入力フォーム'!E104
A95: 91 | B95: 8 | C95: 技術・OCI期待範囲 | D95: F808 | E95: Oracle/OCIに相談したいこと | F95: OracleQuestions | G95: 任意 | H95: ='入力フォーム'!E105
A96: 92 | B96: 9 | C96: セキュリティ / ガバナンス | D96: F901 | E96: セキュリティ要件 | F96: SecurityRequirements | G96: 任意 | H96: ='入力フォーム'!E107
A97: 93 | B97: 9 | C97: セキュリティ / ガバナンス | D97: F902 | E97: 法規制・コンプライアンス | F97: ComplianceRequirements | G97: 任意 | H97: ='入力フォーム'!E108
A98: 94 | B98: 9 | C98: セキュリティ / ガバナンス | D98: F903 | E98: AI利用上の懸念・NG領域 | F98: AIRisksNG | G98: 任意 | H98: ='入力フォーム'!E109
A99: 95 | B99: 9 | C99: セキュリティ / ガバナンス | D99: F904 | E99: 監査・ログ・運用管理 | F99: AuditMonitoring | G99: 任意 | H99: ='入力フォーム'!E110
A100: 96 | B100: 9 | C100: セキュリティ / ガバナンス | D100: F905 | E100: 本番データ利用可能性 | F100: ProductionDataAvailability | G100: 任意 | H100: ='入力フォーム'!E111
A101: 97 | B101: 9 | C101: セキュリティ / ガバナンス | D101: F906 | E101: 生成AI利用に関する社内承認状況 | F101: GenAIApprovalStatus | G101: 任意 | H101: ='入力フォーム'!E112
A102: 98 | B102: 10 | C102: PoC・評価条件・提出資料 | D102: F1001 | E102: PoC対象顧客・対象業務 | F102: PoCTarget | G102: 任意 | H102: ='入力フォーム'!E114
A103: 99 | B103: 10 | C103: PoC・評価条件・提出資料 | D103: F1002 | E103: 評価指標・本番化判断基準 | F103: PoCEvaluationCriteria | G103: 任意 | H103: ='入力フォーム'!E115
A104: 100 | B104: 10 | C104: PoC・評価条件・提出資料 | D104: F1003 | E104: 希望スケジュール | F104: DesiredTimeline | G104: 任意 | H104: ='入力フォーム'!E116
A105: 101 | B105: 10 | C105: PoC・評価条件・提出資料 | D105: F1004 | E105: 意思決定者・関係者 | F105: DecisionMakers | G105: 任意 | H105: ='入力フォーム'!E117
A106: 102 | B106: 10 | C106: PoC・評価条件・提出資料 | D106: F1005 | E106: Oracleへの期待・相談事項 | F106: OracleExpectations | G106: 任意 | H106: ='入力フォーム'!E118
A107: 103 | B107: 10 | C107: PoC・評価条件・提出資料 | D107: F1006 | E107: アセスメント後に希望する次アクション | F107: NextAction | G107: 任意 | H107: ='入力フォーム'!E119
A108: 104 | B108: 10 | C108: PoC・評価条件・提出資料 | D108: F1007 | E108: 提出予定資料 | F108: PlannedAttachments | G108: 任意 | H108: ='入力フォーム'!E120
A109: 105 | B109: 10 | C109: PoC・評価条件・提出資料 | D109: F1008 | E109: 関連資料アップロード | F109: AttachmentLinks | G109: 任意 | H109: ='入力フォーム'!E121
A110: 106 | B110: 10 | C110: PoC・評価条件・提出資料 | D110: F1009 | E110: その他補足 | F110: AdditionalNotes | G110: 任意 | H110: ='入力フォーム'!E122
A111: 107 | B111: 10 | C111: PoC・評価条件・提出資料 | D111: F1010 | E111: 入力内容のOracle担当者・事務局への共有可否 | F111: SharePermission | G111: 必須 | H111: ='入力フォーム'!E123

Sheet 入力例_エクス
A1: 入力例_エクス
A2: service_input.txtの内容をもとにした入力例です。実際の回答は各社の状況に合わせて変更してください。
A4: 質問ID | B4: 設問 | C4: 入力例 | D4: 出典メモ
A5: F001 | B5: 情報利用目的を確認しましたか？
A6: F002 | B6: 本番データ・顧客機密データ・個人情報をアップロードしないことを確認しましたか？
A7: F101 | B7: 会社名 | C7: 株式会社エクス | D7: service_input.txt / HTMLフォームのサンプル値を要約
A8: F102 | B8: 会社URL | C8: https://www.xeex.co.jp/ | D8: service_input.txt / HTMLフォームのサンプル値を要約
A9: F103 | B9: 事業概要 | C9: 製造業向けの生産管理パッケージを中核に、製造業向けクラウドサービス/プラットフォーム、DX関連サービス、導入コンサルティング、カスタマイズ開発、稼働支援、保守を提供するソフトウェアベンダー。 | D9: service_input.txt / HTMLフォームのサンプル値を要約
A10: F104 | B10: 主な顧客像 | C10: 中堅・中小の製造業。生産管理、購買、在庫、現場、販売管理などの部門が主な利用者。 | D10: service_input.txt / HTMLフォームのサンプル値を要約
A11: F105 | B11: 対象業種・業態 | C11: 製造業;生産管理;販売管理;サプライチェーン;調達・購買 | D11: service_input.txt / HTMLフォームのサンプル値を要約
A12: F106 | B12: 自社の強み・保有IP | C12: 生産・販売統合型の業務ロジック、製造業向けマスタ/実績データ、導入実績、周辺DXソリューションとの接続可能性。 | D12: service_input.txt / HTMLフォームのサンプル値を要約
A13: F107 | B13: 入力者氏名
A14: F108 | B14: 入力者メール
A15: F109 | B15: 入力者所属/役職
A16: F201 | B16: 今回のAssessment対象範囲
A17: F202 | B17: 対象プロジェクト数
A18: F211 | B18: プロジェクト1：プロジェクト/製品名 | C18: Factory-ONE 電脳工場 データ活用 | D18: service_input.txt / HTMLフォームのサンプル値を要約
A19: F212 | B19: プロジェクト1：段階 | C19: 本番運用中 | D19: service_input.txt / HTMLフォームのサンプル値を要約
A20: F213 | B20: プロジェクト1：優先度 | C20: 高 | D20: service_input.txt / HTMLフォームのサンプル値を要約
A21: F214 | B21: プロジェクト1：AI活用の狙い・確認したいこと | C21: 既存データを活用し、需給・在庫、生産計画、原価・調達のAIユースケースを検討する。 | D21: service_input.txt / HTMLフォームのサンプル値を要約
A22: F221 | B22: プロジェクト2：プロジェクト/製品名 | C22: こうばWith | D22: service_input.txt / HTMLフォームのサンプル値を要約
A23: F222 | B23: プロジェクト2：段階 | C23: 本番環境構築中 | D23: service_input.txt / HTMLフォームのサンプル値を要約
A24: F223 | B24: プロジェクト2：優先度 | C24: 中 | D24: service_input.txt / HTMLフォームのサンプル値を要約
A25: F224 | B25: プロジェクト2：AI活用の狙い・確認したいこと | C25: 本番データの種類、保持場所、テナント構成、運用監視、AI機能の段階導入可否を確認する。 | D25: service_input.txt / HTMLフォームのサンプル値を要約
A26: F231 | B26: プロジェクト3：プロジェクト/製品名 | C26: Endeval（旧Endevor） | D26: service_input.txt / HTMLフォームのサンプル値を要約
A27: F232 | B27: プロジェクト3：段階 | C27: 開発中 | D27: service_input.txt / HTMLフォームのサンプル値を要約
A28: F233 | B28: プロジェクト3：優先度 | C28: 中 | D28: service_input.txt / HTMLフォームのサンプル値を要約
A29: F234 | B29: プロジェクト3：AI活用の狙い・確認したいこと | C29: 構成検討中のため、事業目的、対象業務、アーキテクチャ、AI活用の狙いを整理する。 | D29: service_input.txt / HTMLフォームのサンプル値を要約
... A39: F402 | B39: 価格形態 | C39: 月額サブスクリプション;保守費;個別見積 | D39: service_input.txt / HTMLフォームのサンプル値を要約
A40: F403 | B40: ライセンス形式
A41: F404 | B41: 現行収益モデル | C41: パッケージ/クラウド利用料、導入コンサルティング、カスタマイズ開発、稼働支援、保守。 | D41: service_input.txt / HTMLフォームのサンプル値を要約
A42: F405 | B42: AI機能の想定収益モデル | C42: AIアドオン;上位プラン;AI Agent実行回数課金;標準機能化による解約率低減 | D42: service_input.txt / HTMLフォームのサンプル値を要約
A43: F406 | B43: 主な競合製品・競合企業 | C43: 同業生産管理パッケージ、ERP、製造業向けSaaS、内製システム。詳細は顧客ヒアリングで確認。 | D43: service_input.txt / HTMLフォームのサンプル値を要約
A44: F407 | B44: 競合と比較したAI差別化仮説 | C44: 生産管理・販売管理・EDI・現場帳票などのデータを横断し、需要予測、納期遅延予兆、在庫リスク、調達価格影響を説明できるAI機能を提供することで差別化する仮説。 | D44: service_input.txt / HTMLフォームのサンプル値を要約
A45: F408 | B45: 市場投入上の課題・懸念
A46: F501 | B46: 保有データ・業務IP | C46: 品目マスタ、BOM、取引先、工程、受注、出荷、生産計画、発注、受入、在庫、負荷、進捗、原価、請求、売掛、入金、仕入、買掛、支払、EDI取引、現場帳票、問い合わせ/マニュアル。 | D46: service_input.txt / HTMLフォームのサンプル値を要約
A47: F502 | B47: データ種別 | C47: マスタデータ;トランザクション;文書/PDF/マニュアル;外部データ/API;複数企業間データ | D47: service_input.txt / HTMLフォームのサンプル値を要約
A48: F503 | B48: データの所在・保持場所 | C48: 自社SaaS DB;顧客環境;外部基幹システム;EDI/外部取引基盤;ファイル/文書ストレージ | D48: service_input.txt / HTMLフォームのサンプル値を要約
A49: F504 | B49: データ形式・連携方式 | C49: RDB;CSV;API;EDI;PDF/文書;画像/帳票 | D49: service_input.txt / HTMLフォームのサンプル値を要約
A50: F505 | B50: データ量・更新頻度・品質 | C50: データ量、履歴期間、欠損、表記揺れ、マスタ整備状況、更新頻度は初回ヒアリングで確認。 | D50: service_input.txt / HTMLフォームのサンプル値を要約
A51: F506 | B51: テナント分離・顧客データ方針 | C51: 顧客テナントごとのデータ分離、顧客データ利用許諾、匿名化/マスキング方針を確認。 | D51: service_input.txt / HTMLフォームのサンプル値を要約
A52: F507 | B52: データ利用許諾・匿名化/マスキング | C52: PoCで利用可能なサンプルデータ、匿名化データ、本番データ利用可否、顧客同意範囲を確認。 | D52: service_input.txt / HTMLフォームのサンプル値を要約
A53: F508 | B53: 複数企業/取引先データの取り扱い | C53: EDIFAS等の複数企業データについて、利用目的、データ所有権、同意、越境/共有範囲を最初に整理する。 | D53: service_input.txt / HTMLフォームのサンプル値を要約
A54: F509_1 | B54: データ成熟度：必要データが存在する
A55: F509_2 | B55: データ成熟度：データ項目定義が明確
A56: F509_3 | B56: データ成熟度：データ品質を把握している
A57: F509_4 | B57: データ成熟度：顧客データ利用許諾が整理済み
A58: F509_5 | B58: データ成熟度：匿名化・マスキング方針がある
A59: F509_6 | B59: データ成熟度：API・連携方式がある
A60: F601 | B60: AI活用目的 | C60: 新サービス開発・収益増;競合差別化;業務効率化・運用効率化;顧客体験向上;コスト/原価率改善 | D60: service_input.txt / HTMLフォームのサンプル値を要約
A61: F602 | B61: AIで何を行いたいか | C61: 需給・在庫の予測、欠品/過剰在庫リスク検知、納期遅延予兆、負荷偏り検知、調達価格変動の利益影響予測、製造・生産管理の問い合わせ対応、マニュアル/過去事例検索。 | D61: service_input.txt / HTMLフォームのサンプル値を要約
A62: F603 | B62: 期待するAI機能・サービス内容 | C62: RAG/ナレッジ検索;自然言語でのデータ問い合わせ;予測;異常検知;AI Agentによる業務実行支援;文書/帳票生成 | D62: service_input.txt / HTMLフォームのサンプル値を要約
A63: F604 | B63: AIの実行レベル | C63: 提案・推奨まで | D63: service_input.txt / HTMLフォームのサンプル値を要約
A64: F605 | B64: 人による確認/承認が必要な場面 | C64: 計画変更、発注、外部通知、価格提示、顧客データをまたぐ分析は人間承認を前提とする。 | D64: service_input.txt / HTMLフォームのサンプル値を要約
A65: F606 | B65: 期待するKPI/ビジネス効果 | C65: 在庫削減、欠品/過剰在庫の抑制、納期遵守率向上、問い合わせ対応時間削減、計画変更判断の迅速化、AI機能による新規収益化。 | D65: service_input.txt / HTMLフォームのサンプル値を要約
A66: F607 | B66: AI機能の想定利用者
A67: F711 | B67: ユースケース1：名称 | C67: 需要予測・在庫最適化 | D67: service_input.txt / HTMLフォームのサンプル値を要約
A68: F712 | B68: ユースケース1：業務領域 | C68: 需給・在庫 | D68: service_input.txt / HTMLフォームのサンプル値を要約
A69: F713 | B69: ユースケース1：優先度 | C69: 高 | D69: service_input.txt / HTMLフォームのサンプル値を要約
A70: F714 | B70: ユースケース1：利用シナリオ | C70: 販売/受注/在庫履歴から将来需要を予測し、安全在庫・発注点を提案する。 | D70: service_input.txt / HTMLフォームのサンプル値を要約
A71: F715 | B71: ユースケース1：必要データ | C71: 販売/受注履歴、在庫、品目、BOM、リードタイム、発注履歴、季節性データ。 | D71: service_input.txt / HTMLフォームのサンプル値を要約
A72: F716 | B72: ユースケース1：想定AI技術 | C72: 予測/時系列分析;生成AI;データ可視化 | D72: service_input.txt / HTMLフォームのサンプル値を要約
A73: F717 | B73: ユースケース1：期待効果/KPI | C73: 在庫削減率、欠品率、過剰在庫額、発注判断時間。 | D73: service_input.txt / HTMLフォームのサンプル値を要約
A74: F721 | B74: ユースケース2：名称 | C74: 納期遅延予兆・計画変更影響説明 | D74: service_input.txt / HTMLフォームのサンプル値を要約
A75: F722 | B75: ユースケース2：業務領域 | C75: 生産計画・進捗 | D75: service_input.txt / HTMLフォームのサンプル値を要約
A76: F723 | B76: ユースケース2：優先度 | C76: 高 | D76: service_input.txt / HTMLフォームのサンプル値を要約
A77: F724 | B77: ユースケース2：利用シナリオ | C77: 生産計画、進捗、負荷、在庫、購買状況をもとに遅延リスクを検知し、影響範囲を自然言語で説明する。 | D77: service_input.txt / HTMLフォームのサンプル値を要約
A78: F725 | B78: ユースケース2：必要データ | C78: 生産計画、進捗、負荷、工程、受注、納期変更履歴、購買/在庫。 | D78: service_input.txt / HTMLフォームのサンプル値を要約
... A88: F801 | B88: 現行アーキテクチャ概要 | C88: 現行プラットフォーム、DB、API、認証、テナント構成、データ連携図を確認。 | D88: service_input.txt / HTMLフォームのサンプル値を要約
A89: F802 | B89: 利用中クラウド/基盤
A90: F803 | B90: 利用中DB/データ基盤
A91: F804 | B91: API・認証・外部連携 | C91: 外部基幹システムとのAPI/CSV連携、EDI、認証、権限制御、既存業務画面との連携方式を確認。 | D91: service_input.txt / HTMLフォームのサンプル値を要約
A92: F805 | B92: OCI上で求める範囲 | C92: データ基盤;生成AI;RAG;AI Agent;Vector Search;アプリ連携;セキュリティ;監視・運用 | D92: service_input.txt / HTMLフォームのサンプル値を要約
A93: F806 | B93: 非機能要件 | C93: 画面応答、AI回答時間、可用性、コスト、監査ログ、DR、運用監視、マルチテナント性能。 | D93: service_input.txt / HTMLフォームのサンプル値を要約
A94: F807 | B94: 既存制約・移行条件
A95: F808 | B95: Oracle/OCIに相談したいこと
A96: F901 | B96: セキュリティ要件 | C96: テナント分離;暗号化;アクセス制御;監査ログ;プロンプト/入力制御;出力フィルタリング | D96: service_input.txt / HTMLフォームのサンプル値を要約
A97: F902 | B97: 法規制・コンプライアンス | C97: 個人情報、電子帳簿保存法、顧客契約、企業間データ共有、越境/共有範囲。 | D97: service_input.txt / HTMLフォームのサンプル値を要約
A98: F903 | B98: AI利用上の懸念・NG領域 | C98: 誤回答、説明責任、計画/発注への自動反映範囲、複数企業データの利用、プロンプトインジェクション。 | D98: service_input.txt / HTMLフォームのサンプル値を要約
A99: F904 | B99: 監査・ログ・運用管理 | C99: 質問履歴、参照データ、回答根拠、承認履歴、AI提案の採用/却下ログ。 | D99: service_input.txt / HTMLフォームのサンプル値を要約
A100: F905 | B100: 本番データ利用可能性
A101: F906 | B101: 生成AI利用に関する社内承認状況
A102: F1001 | B102: PoC対象顧客・対象業務 | C102: 既存データが存在する電脳工場で価値仮説とデータ可用性を確認し、EDIFAS等の周辺データ接続可能性を評価。 | D102: service_input.txt / HTMLフォームのサンプル値を要約
A103: F1002 | B103: 評価指標・本番化判断基準 | C103: 回答精度、予測精度、業務時間削減、在庫/納期KPI改善、レスポンス、コスト、ユーザー評価。 | D103: service_input.txt / HTMLフォームのサンプル値を要約
A104: F1003 | B104: 希望スケジュール | C104: 3ヶ月以内 | D104: service_input.txt / HTMLフォームのサンプル値を要約
A105: F1004 | B105: 意思決定者・関係者 | C105: 事業責任者、CTO、プロダクト責任者、開発責任者、データ責任者、営業責任者。 | D105: service_input.txt / HTMLフォームのサンプル値を要約
A106: F1005 | B106: Oracleへの期待・相談事項
A107: F1006 | B107: アセスメント後に希望する次アクション | C107: AI Use Case Assessment実施;RAG/Agent PoC;AI Database検証;セキュリティ相談 | D107: service_input.txt / HTMLフォームのサンプル値を要約
A108: F1007 | B108: 提出予定資料 | C108: 製品紹介資料;画面キャプチャ;API仕様;データ項目一覧;業務フロー;システム構成図;FAQ;マニュアル;サンプルデータ | D108: service_input.txt / HTMLフォームのサンプル値を要約
A109: F1008 | B109: 関連資料アップロード
A110: F1009 | B110: その他補足 | C110: 3プロジェクトの事業KPI、優先課題、意思決定者、リリース時期、データ利用許諾、連携図、PoC評価指標を初回ヒアリングで確定する。 | D110: service_input.txt / HTMLフォームのサンプル値を要約
A111: F1010 | B111: 入力内容のOracle担当者・事務局への共有可否

Sheet 選択肢一覧
A1: 選択肢一覧
A2: 入力フォームのプルダウンに利用する選択肢です。複数選択項目はフォーム上で「;」区切りで入力可能です。
A4: F001 | B4: F002 | C4: F105 | D4: F201 | E4: F202 | F4: F212 | G4: F213 | H4: F222 | I4: F223 | J4: F232 | K4: F233 | L4: F302 | M4: F401 | N4: F402 | O4: F403 | P4: F405 | Q4: F502 | R4: F503 | S4: F504 | T4: F509_1 | U4: F509_2 | V4: F509_3 | W4: F509_4 | X4: F509_5 | Y4: F509_6 | Z4: F601 | AA4: F603 | AB4: F604 | AC4: F607 | AD4: F712 | AE4: F713 | AF4: F716 | AG4: F722 | AH4: F723 | AI4: F726 | AJ4: F732 | AK4: F733 | AL4: F736 | AM4: F802 | AN4: F803 | AO4: F805 | AP4: F901 | AQ4: F905 | AR4: F906 | AS4: F1003 | AT4: F1006 | AU4: F1007 | AV4: F1010
A5: 情報利用目的を確認しましたか？ | B5: 本番データ・顧客機密データ・個人情報をアップロードしないことを確認しましたか？ | C5: 対象業種・業態 | D5: 今回のAssessment対象範囲 | E5: 対象プロジェクト数 | F5: プロジェクト1：段階 | G5: プロジェクト1：優先度 | H5: プロジェクト2：段階 | I5: プロジェクト2：優先度 | J5: プロジェクト3：段階 | K5: プロジェクト3：優先度 | L5: 提供形態 | M5: ターゲット顧客規模 | N5: 価格形態 | O5: ライセンス形式 | P5: AI機能の想定収益モデル | Q5: データ種別 | R5: データの所在・保持場所 | S5: データ形式・連携方式 | T5: データ成熟度：必要データが存在する | U5: データ成熟度：データ項目定義が明確 | V5: データ成熟度：データ品質を把握している | W5: データ成熟度：顧客データ利用許諾が整理済み | X5: データ成熟度：匿名化・マスキング方針がある | Y5: データ成熟度：API・連携方式がある | Z5: AI活用目的 | AA5: 期待するAI機能・サービス内容 | AB5: AIの実行レベル | AC5: AI機能の想定利用者 | AD5: ユースケース1：業務領域 | AE5: ユースケース1：優先度 | AF5: ユースケース1：想定AI技術 | AG5: ユースケース2：業務領域 | AH5: ユースケース2：優先度 | AI5: ユースケース2：想定AI技術 | AJ5: ユースケース3：業務領域 | AK5: ユースケース3：優先度 | AL5: ユースケース3：想定AI技術 | AM5: 利用中クラウド/基盤 | AN5: 利用中DB/データ基盤 | AO5: OCI上で求める範囲 | AP5: セキュリティ要件 | AQ5: 本番データ利用可能性 | AR5: 生成AI利用に関する社内承認状況 | AS5: 希望スケジュール | AT5: アセスメント後に希望する次アクション | AU5: 提出予定資料 | AV5: 入力内容のOracle担当者・事務局への共有可否
A6: 確認しました | B6: 確認しました | C6: 製造業 | D6: 既存SaaS/クラウドサービス | E6: 1件 | F6: 本番運用中 | G6: 高 | H6: 本番運用中 | I6: 高 | J6: 本番運用中 | K6: 高 | L6: SaaS | M6: SMB | N6: 月額サブスクリプション | O6: Named User | P6: AIアドオン | Q6: マスタデータ | R6: 自社SaaS DB | S6: RDB | T6: 未整理 | U6: 未整理 | V6: 未整理 | W6: 未整理 | X6: 未整理 | Y6: 未整理 | Z6: 新サービス開発・収益増 | AA6: RAG/ナレッジ検索 | AB6: 説明/回答のみ | AC6: エンドユーザー | AD6: 需給・在庫 | AE6: 高 | AF6: 生成AI | AG6: 需給・在庫 | AH6: 高 | AI6: 生成AI | AJ6: 需給・在庫 | AK6: 高 | AL6: 生成AI | AM6: AWS | AN6: Oracle Database | AO6: データ基盤 | AP6: テナント分離 | AQ6: 利用不可 | AR6: 承認済み | AS6: 1ヶ月以内 | AT6: AI Use Case Assessment実施 | AU6: 製品紹介資料 | AV6: 共有可
C7: 流通/小売 | D7: 既存パッケージ | E7: 2件 | F7: 本番環境構築中 | G7: 中 | H7: 本番環境構築中 | I7: 中 | J7: 本番環境構築中 | K7: 中 | L7: パッケージ | M7: 中堅企業 | N7: 年額サブスクリプション | O7: Concurrent User | P7: 上位プラン | Q7: トランザクション | R7: 顧客環境 | S7: CSV | T7: 一部整理 | U7: 一部整理 | V7: 一部整理 | W7: 一部整理 | X7: 一部整理 | Y7: 一部整理 | Z7: 競合差別化 | AA7: 自然言語でのデータ問い合わせ | AB7: 提案・推奨まで | AC7: 管理者 | AD7: 生産計画・進捗 | AE7: 中 | AF7: RAG | AG7: 生産計画・進捗 | AH7: 中 | AI7: RAG | AJ7: 生産計画・進捗 | AK7: 中 | AL7: RAG | AM7: Azure | AN7: PostgreSQL | AO7: 生成AI | AP7: 暗号化 | AQ7: 匿名化データのみ可 | AR7: 条件付き承認 | AS7: 3ヶ月以内 | AT7: RAG/Agent PoC | AU7: 画面キャプチャ | AV7: 個別範囲を相談
C8: 金融 | D8: 新規サービス/新規SaaS | E8: 3件以上 | F8: 開発中 | G8: 低 | H8: 開発中 | I8: 低 | J8: 開発中 | K8: 低 | L8: オンプレミス | M8: 大企業 | N8: ユーザー課金 | O8: Site License | P8: 利用量課金 | Q8: 文書/PDF/マニュアル | R8: 外部基幹システム | S8: API | T8: 整理済み | U8: 整理済み | V8: 整理済み | W8: 整理済み | X8: 整理済み | Y8: 整理済み | Z8: 業務効率化・運用効率化 | AA8: 要約 | AB8: 人間承認後に実行 | AC8: 経営/管理職 | AD8: 原価・調達 | AE8: 低 | AF8: Vector Search | AG8: 原価・調達 | AH8: 低 | AI8: Vector Search | AJ8: 原価・調達 | AK8: 低 | AL8: Vector Search | AM8: Google Cloud | AN8: MySQL | AO8: RAG | AP8: アクセス制御 | AQ8: サンプルデータのみ可 | AR8: 申請中 | AS8: 6ヶ月以内 | AT8: AI Database検証 | AU8: API仕様 | AV8: 共有不可
C9: 医療/ヘルスケア | D9: 本番環境構築中 | E9: 未定 | F9: 構想中 | G9: 未定 | H9: 構想中 | I9: 未定 | J9: 構想中 | K9: 未定 | L9: クラウドサービス | M9: エンタープライズ | N9: テナント課金 | O9: Tenant License | P9: AI Agent実行回数課金 | Q9: ログ/利用履歴 | R9: ファイル/文書ストレージ | S9: EDI | T9: 検証済み | U9: 検証済み | V9: 検証済み | W9: 検証済み | X9: 検証済み | Y9: 検証済み | Z9: 顧客体験向上 | AA9: 文書/帳票生成 | AB9: 条件付きで自動実行 | AC9: サポート担当 | AD9: 業務支援 | AE9: 未定 | AF9: AI Agent | AG9: 業務支援 | AH9: 未定 | AI9: AI Agent | AJ9: 業務支援 | AK9: 未定 | AL9: AI Agent | AM9: OCI | AN9: SQL Server | AO9: AI Agent | AP9: 監査ログ | AQ9: 条件付きで本番データ可 | AR9: 未承認 | AS9: FY内 | AT9: OCI移行/コスト相談 | AU9: データ項目一覧
C10: 公共 | D10: 開発中 | F10: PoC中 | H10: PoC中 | J10: PoC中 | L10: プラットフォーム | M10: 公共 | N10: API/利用量課金 | O10: Device/拠点課金 | P10: 帳票/文書処理件数課金 | Q10: 画像/図面/帳票 | R10: DWH/Datamart | S10: PDF/文書 | T10: 不明 | U10: 不明 | V10: 不明 | W10: 不明 | X10: 不明 | Y10: 不明 | Z10: 従業員体験向上 | AA10: 予測 | AB10: 完全自動実行を検討 | AC10: 開発/運用担当 | AD10: サプライチェーン | AF10: 自然言語SQL/NL2SQL | AG10: サプライチェーン | AI10: 自然言語SQL/NL2SQL | AJ10: サプライチェーン | AL10: 自然言語SQL/NL2SQL | AM10: オンプレミス | AN10: NoSQL | AO10: Vector Search | AP10: ネットワーク分離 | AQ10: 個別合意後に判断 | AR10: 未確認 | AS10: 未定 | AT10: セキュリティ相談 | AU10: 業務フロー
C11: 建設 | D11: 構想中 | F11: 未定 | H11: 未定 | J11: 未定 | L11: 導入支援/コンサル | M11: 海外 | N11: 初期費用 | O11: API Call | P11: 成果/業務KPI連動 | Q11: 音声/会話 | R11: Object Storage | S11: 画像/帳票 | Z11: コスト/原価率改善 | AA11: 異常検知 | AB11: 未定 | AC11: 顧客企業のIT部門 | AD11: 製品開発・運用 | AF11: 予測/時系列分析 | AG11: 製品開発・運用 | AI11: 予測/時系列分析 | AJ11: 製品開発・運用 | AL11: 予測/時系列分析 | AM11: 自社DC | AN11: DWH | AO11: アプリ連携 | AP11: キー管理 | AQ11: 未定 | AT11: 共同GTM/Marketplace検討 | AU11: システム構成図
C12: バックオフィス | D12: 複数プロジェクト横断 | L12: 保守/運用支援 | M12: 未定 | N12: 保守費 | O12: Transaction | P12: 標準機能化による解約率低減 | Q12: 外部データ/API | R12: EDI/外部取引基盤 | S12: ログ | Z12: リスク低減・品質向上 | AA12: 最適化/推薦 | AC12: 取引先/サプライヤー | AD12: カスタマーサポート | AF12: 異常検知 | AG12: カスタマーサポート | AI12: 異常検知 | AJ12: カスタマーサポート | AL12: 異常検知 | AM12: SaaS/PaaS | AN12: Data Lake | AO12: セキュリティ | AP12: データ保管場所 | AT12: 未定 | AU12: FAQ
C13: 物流/SCM | L13: その他 | N13: ライセンス買い切り | O13: その他 | P13: 未定 | Q13: 複数企業間データ | R13: 未定 | S13: 音声 | Z13: 開発生産性向上 | AA13: 画像・帳票認識 | AC13: その他 | AD13: セキュリティ | AF13: 最適化 | AG13: セキュリティ | AI13: 最適化 | AJ13: セキュリティ | AL13: 最適化 | AM13: 未定/非公開 | AN13: Search Engine | AO13: 監視・運用 | AP13: 脆弱性管理 | AU13: マニュアル
C14: 教育 | N14: 個別見積 | Q14: 個人情報/機密情報を含む | S14: その他 | AA14: 音声/議事録 | AD14: その他 | AF14: 画像認識 | AG14: その他 | AI14: 画像認識 | AJ14: その他 | AL14: 画像認識 | AN14: その他 | AO14: 移行/マルチクラウド | AP14: プロンプト/入力制御 | AU14: サンプルデータ
C15: 不動産 | AA15: AI Agentによる業務実行支援 | AF15: 文書理解/OCR | AI15: 文書理解/OCR | AL15: 文書理解/OCR | AO15: PoC環境 | AP15: 出力フィルタリング | AU15: なし/後日
C16: その他 | AA16: コード/開発支援 | AF16: 音声認識 | AI16: 音声認識 | AL16: 音声認識 | AO16: 未定
AA17: 運用監視 | AF17: データ可視化 | AI17: データ可視化 | AL17: データ可視化
AF18: Human-in-the-loop | AI18: Human-in-the-loop | AL18: Human-in-the-loop

Sheet Sources
A1: Sources
A2: 本ワークブックで参照したファイル・資料です。スプレッドシート内ではURL/ファイルパスをプレーンテキストで記載しています。
A4: 区分 | B4: 資料/ページ | C4: URL/ファイル | D4: 用途
A5: Uploaded file | B5: service_input.txt | C5: /mnt/data/service_input.txt | D5: 株式会社エクスのサンプル内容、製品/サービス、AI論点、ヒアリング項目の元資料
A6: Uploaded/generated file | B6: isv_ai_use_case_assessment_input_form.html | C6: /mnt/data/isv_ai_use_case_assessment_input_form.html | D6: HTMLフォームの10セクション・項目構成・サンプル値
A7: Generated file | B7: ISV_AI_Use_Case_Assessment_MSForms_Format.xlsx | C7: /mnt/data/ISV_AI_Use_Case_Assessment_MSForms_Format.xlsx | D7: Microsoft Forms設計書、SharePoint列定義、設問定義
A8: Microsoft Support | B8: Microsoft Formsでフォームを作成 | C8: https://support.microsoft.com/ja-jp/forms/create-a-form-with-microsoft-forms | D8: Forms設問タイプ/セクション化の参考
A9: Microsoft Support | B9: SharePoint WebパーツでMicrosoft Formsを利用 | C9: https://support.microsoft.com/ja-jp/forms/use-the-microsoft-forms-web-part-on-a-sharepoint-site | D9: SharePoint共有/埋め込みの参考
A10: Microsoft Support | B10: Power AutomateでMicrosoft Forms回答を処理 | C10: https://support.microsoft.com/ja-jp/forms/create-an-automated-workflow-for-microsoft-forms | D10: SharePoint List登録フローの参考
